<http-page executeResourcesDynamically="false" name="/qaphr998/"
    playRequestsSequentially="false"
    recordedArtifactZipFileName="team/vus/@prism@h@r_@payroll_@c4635756_@o@l@ds/%resources%/recorded-artifacts/340d258d-103b-43b9-838b-54f6a89ebdc7.zip"
    slaProfileEnabled="false" thinkTime="6009"
    thinkTimeMode="MODE_SIMPLE_THINK_TIME" thinkTimeRangeEnd=""
    thinkTimeRangeStart="" uid="340d258d-103b-43b9-838b-54f6a89ebdc7">
    <embedded-action>60c90ac4-bb7b-4789-8888-bf1684b0b835</embedded-action>
    <embedded-action>f69c6a6a-64fd-43f8-b331-e7add26779c3</embedded-action>
    <embedded-action>98cb8339-e80d-49bb-a3ea-d3828b9dec4a</embedded-action>
    <embedded-action>3c093a11-a3c2-478e-a62e-72f3af506bfe</embedded-action>
    <embedded-action>f6b897af-5237-4b98-a670-f2366b55ea0d</embedded-action>
    <embedded-action>d02675f1-e236-46d7-b999-e98419bfdbfd</embedded-action>
    <embedded-action>8ac3f6b9-f90d-46ab-8183-be24ce0d00a4</embedded-action>
    <embedded-action>4af70c95-d23f-4e44-872b-29a27e2951fc</embedded-action>
    <embedded-action>92268e1c-df76-469f-9ec3-b085fa6d4739</embedded-action>
    <embedded-action>86279270-5043-492b-956b-928f42f8fe60</embedded-action>
    <embedded-action>d46fbaa0-5cb8-44c7-9c65-e3eebb6ec46c</embedded-action>
    <embedded-action>3424114e-b66a-47f1-9527-d8266a10dbc9</embedded-action>
    <embedded-action>178bab4d-2975-489b-8040-6c527151eb29</embedded-action>
    <embedded-action>d37668ff-adc4-4df5-b310-ccc3f453076f</embedded-action>
    <embedded-action>06a2253c-67c5-43ab-bbd6-c7187894ddb6</embedded-action>
    <embedded-action>89d4f531-ff81-4ec5-9908-6ff1da3e34cc</embedded-action>
    <embedded-action>787a7f7c-7495-45d3-bab7-39b3aeb6b3f9</embedded-action>
    <embedded-action>e49e57d1-454a-4912-a169-1a9e8b2e8a58</embedded-action>
    <embedded-action>00ecd9c7-6240-48a2-83dd-22112e1a60ec</embedded-action>
</http-page>
<http-action actionType="1" contentType="text/html; charset=utf-8"
    extractorInjectPathPolicy="2" extractorPathPolicy="1"
    followRedirects="false" generatedByClient="false"
    linkExtractorSeveralMatchOccurrence="1"
    linkExtractorSeveralMatchPolicy="1" linkExtractorType="6"
    method="POST" name="/qaphr998/" path="/qaphr998/" postCharset=""
    postType="4"
    recordedArtifactZipFileName="team/vus/@prism@h@r_@payroll_@c4635756_@o@l@ds/%resources%/recorded-artifacts/340d258d-103b-43b9-838b-54f6a89ebdc7.zip"
    recordedResponseCode="200" responseSize="684894"
    serverUid="imported_qaphr998.prismhr.com" slaProfileEnabled="false"
    uid="60c90ac4-bb7b-4789-8888-bf1684b0b835" useKeepAlive="false">
    <responsePageFileDescription>recorded-responses/res_aa8327f7-b278-42e5-80a9-f0c3fd067b45.html</responsePageFileDescription>
    <requestContentFileDescription>recorded-requests/req_aa8327f7-b278-42e5-80a9-f0c3fd067b45.txt</requestContentFileDescription>
    <variable-extractor assertionOnNoMatch="true"
        defaultValue="&lt;NOT FOUND>" displayMode="1" endsWithSimple=""
        extractFromVarNameAdv="" extractFromVarNameSimple=""
        extractType="1" extractTypeAdv="1" extractTypeSimple="0"
        matchNumber="1" matchNumberAdv="1" matchNumberSimple="1"
        name="IDBrowser" regExp="IDBrowser=(.*?);"
        regExpAdv="IDBrowser=(.*?);" setDefaultValue="true"
        startsWithSimple="" template="$1$" templateAdv="$1$"
        uid="faae2ea3-ecb4-4ebb-ab08-735b6d3785e4" xpath=""/>
    <variable-extractor assertionOnNoMatch="true"
        defaultValue="&lt;NOT FOUND>" displayMode="0"
        endsWithSimple="');" extractFromVarNameAdv=""
        extractFromVarNameSimple="" extractType="0" extractTypeAdv="0"
        extractTypeSimple="0" matchNumber="1" matchNumberAdv="1"
        matchNumberSimple="1" name="Design_Bais"
        refererUid="767f76db-9054-4a61-8d7d-3fd6921b103d"
        regExp="\('designbaisState', '(.*?)'\);" regExpAdv=""
        setDefaultValue="true" startsWithSimple="('designbaisState', '"
        template="$1$" templateAdv="$1$"
        uid="dd1209f3-0f47-48c7-b6b0-d8b7816529e6" xpath="">
        <variable-extractor-group extract="true" occurs="1" pattern="" type="4"/>
    </variable-extractor>
    <header name="Accept" value="*/*"/>
    <header name="Accept-Encoding" value="gzip, deflate, br"/>
    <header name="Accept-Language" value="en-US,en;q=0.9"/>
    <header name="Connection" value="keep-alive"/>
    <header name="Content-Type" value="text/xml"/>
    <header name="Cookie" value="DesignBAIS=machine=BRGJRUIQQZBQESBROORAVVEEUDTAPPBTAZWMPIOOHUNGCOS&amp;pooler=537&amp;ver=40; IDBrowser=${IDBrowser}"/>
    <header name="Host" value="qaphr998.prismhr.com"/>
    <header name="Origin" value="https://qaphr998.prismhr.com"/>
    <header name="Referer" value="https://qaphr998.prismhr.com/qaphr998/"/>
    <header name="sec-ch-ua" value="&quot;Not_A Brand&quot;;v=&quot;99&quot;, &quot;Google Chrome&quot;;v=&quot;109&quot;, &quot;Chromium&quot;;v=&quot;109&quot;"/>
    <header name="sec-ch-ua-mobile" value="?0"/>
    <header name="sec-ch-ua-platform" value="&quot;Windows&quot;"/>
    <header name="Sec-Fetch-Dest" value="empty"/>
    <header name="Sec-Fetch-Mode" value="cors"/>
    <header name="Sec-Fetch-Site" value="same-origin"/>
    <header name="User-Agent" value="Mozilla/5.0 (Windows NT 10.0; Win64; x64) AppleWebKit/537.36 (KHTML, like Gecko) Chrome/109.0.0.0 Safari/537.36"/>
    <header name="X-Requested-With" value="XMLHttpRequest"/>
    <responseHeaders>HTTP/1.1 200 OK&#xd;
Cache-Control: private&#xd;
Content-Type: text/html; charset=utf-8&#xd;
Server: Microsoft-IIS/10.0&#xd;
X-AspNet-Version: 4.0.30319&#xd;
Set-Cookie: IDBrowser=06501cba607349608bf6a132a7a101ee3746f7d59fee195b8d055dfd77674cb24xUcaL2PSLeo/cluZWdpBqwubKketl2DQRDnSan0P9A=; expires=Tue, 07-Mar-2023 19:24:39 GMT; path=/; HttpOnly&#xd;
X-Powered-By: ASP.NET&#xd;
Date: Mon, 27 Feb 2023 19:24:41 GMT&#xd;
Content-Length: 684894</responseHeaders>
    <record-html-infos extractorRegExp="false" htmlType="0"/>
    <textPostContent><![CDATA[<AJAX><field  name="text33v1" value=""/><field name="select48v1" value="E"/><field  name="text50v1" value="${Payroll_ID}"/><field  name="tdxspan70v1x-1z3" value="1"/><field  name="" value=""/><field name="select87v1" value="STATUS.TYPE"/><field name="select88v1" value="ALL"/><field name="select89v1" value=""/><field  name="text90v1" value=""/><field  name="textarea95v1" value=""/><field  name="dblastdb1formlayer" value=""/><field  name="ScreenRoot" value="HRPY.WORK_PAYROLL.PROCESSING"/><eventSource>tdxspan76v1x1z1x3</eventSource><eventType>click</eventType><clickPos>425,458,SPAN,tdxspan76v1x1z1x3,166.5,458</clickPos><keyCodes>||||text50v1</keyCodes><dimensions>1903|946|1903|877</dimensions><designbaisState>${Design_Bais}</designbaisState><req>${regkey.dbsuiID}</req><tabStore>${Tstore}</tabStore><captchaKey>null</captchaKey><clientClock>13:24:39</clientClock><clientDate>27.02.2023</clientDate><mobile>false</mobile><lastMVCell></lastMVCell><scrollbarWidth>17</scrollbarWidth></AJAX>]]></textPostContent>
</http-action>
<http-action actionType="1" contentType="image/png"
    eTag="&quot;02f21ed6ded11:0&quot;" extractorInjectPathPolicy="2"
    extractorPathPolicy="1" followRedirects="false"
    generatedByClient="false"
    lastModified="Thu, 14 Jul 2016 19:35:50 GMT"
    linkExtractorSeveralMatchOccurrence="1"
    linkExtractorSeveralMatchPolicy="1" linkExtractorType="6"
    method="GET" name="/qaphr998/images/vision/blueeye.png"
    path="/qaphr998/images/vision/blueeye.png" postType="6"
    recordedArtifactZipFileName="team/vus/@prism@h@r_@payroll_@c4635756_@o@l@ds/%resources%/recorded-artifacts/340d258d-103b-43b9-838b-54f6a89ebdc7.zip"
    recordedResponseCode="200" responseSize="0"
    serverUid="imported_qaphr998.prismhr.com" slaProfileEnabled="false"
    uid="f69c6a6a-64fd-43f8-b331-e7add26779c3" useKeepAlive="false">
    <requestContentFileDescription>recorded-requests/req_fd8d64d4-7bea-4d76-a5b0-252a1a936495.txt</requestContentFileDescription>
    <header name="Accept" value="image/avif,image/webp,image/apng,image/svg+xml,image/*,*/*;q=0.8"/>
    <header name="Accept-Encoding" value="gzip, deflate, br"/>
    <header name="Accept-Language" value="en-US,en;q=0.9"/>
    <header name="Connection" value="keep-alive"/>
    <header name="Cookie" value="DesignBAIS=machine=BRGJRUIQQZBQESBROORAVVEEUDTAPPBTAZWMPIOOHUNGCOS&amp;pooler=537&amp;ver=40; IDBrowser=${IDBrowser}"/>
    <header name="Host" value="qaphr998.prismhr.com"/>
    <header name="Referer" value="https://qaphr998.prismhr.com/qaphr998/"/>
    <header name="sec-ch-ua" value="&quot;Not_A Brand&quot;;v=&quot;99&quot;, &quot;Google Chrome&quot;;v=&quot;109&quot;, &quot;Chromium&quot;;v=&quot;109&quot;"/>
    <header name="sec-ch-ua-mobile" value="?0"/>
    <header name="sec-ch-ua-platform" value="&quot;Windows&quot;"/>
    <header name="Sec-Fetch-Dest" value="image"/>
    <header name="Sec-Fetch-Mode" value="no-cors"/>
    <header name="Sec-Fetch-Site" value="same-origin"/>
    <header name="User-Agent" value="Mozilla/5.0 (Windows NT 10.0; Win64; x64) AppleWebKit/537.36 (KHTML, like Gecko) Chrome/109.0.0.0 Safari/537.36"/>
    <responseHeaders>HTTP/1.1 200 OK&#xd;
Cache-Control: max-age=172800&#xd;
Content-Type: image/png&#xd;
Last-Modified: Thu, 14 Jul 2016 19:35:50 GMT&#xd;
Accept-Ranges: bytes&#xd;
ETag: "02f21ed6ded11:0"&#xd;
Server: Microsoft-IIS/10.0&#xd;
X-Powered-By: ASP.NET&#xd;
Date: Mon, 27 Feb 2023 19:24:41 GMT&#xd;
Content-Length: 453</responseHeaders>
    <record-html-infos extractorRegExp="false" htmlType="0"/>
</http-action>
<http-action actionType="1" contentType="image/png"
    eTag="&quot;062c71e121fd01:0&quot;" extractorInjectPathPolicy="2"
    extractorPathPolicy="1" followRedirects="false"
    generatedByClient="false"
    lastModified="Wed, 24 Dec 2014 00:39:48 GMT"
    linkExtractorSeveralMatchOccurrence="1"
    linkExtractorSeveralMatchPolicy="1" linkExtractorType="6"
    method="GET" name="/qaphr998/images/vision/post.png"
    path="/qaphr998/images/vision/post.png" postType="6"
    recordedArtifactZipFileName="team/vus/@prism@h@r_@payroll_@c4635756_@o@l@ds/%resources%/recorded-artifacts/340d258d-103b-43b9-838b-54f6a89ebdc7.zip"
    recordedResponseCode="200" responseSize="0"
    serverUid="imported_qaphr998.prismhr.com" slaProfileEnabled="false"
    uid="98cb8339-e80d-49bb-a3ea-d3828b9dec4a" useKeepAlive="false">
    <requestContentFileDescription>recorded-requests/req_37ac79ea-e6c7-4180-a602-d7cd9d44dc15.txt</requestContentFileDescription>
    <header name="Accept" value="image/avif,image/webp,image/apng,image/svg+xml,image/*,*/*;q=0.8"/>
    <header name="Accept-Encoding" value="gzip, deflate, br"/>
    <header name="Accept-Language" value="en-US,en;q=0.9"/>
    <header name="Connection" value="keep-alive"/>
    <header name="Cookie" value="DesignBAIS=machine=BRGJRUIQQZBQESBROORAVVEEUDTAPPBTAZWMPIOOHUNGCOS&amp;pooler=537&amp;ver=40; IDBrowser=${IDBrowser}"/>
    <header name="Host" value="qaphr998.prismhr.com"/>
    <header name="Referer" value="https://qaphr998.prismhr.com/qaphr998/"/>
    <header name="sec-ch-ua" value="&quot;Not_A Brand&quot;;v=&quot;99&quot;, &quot;Google Chrome&quot;;v=&quot;109&quot;, &quot;Chromium&quot;;v=&quot;109&quot;"/>
    <header name="sec-ch-ua-mobile" value="?0"/>
    <header name="sec-ch-ua-platform" value="&quot;Windows&quot;"/>
    <header name="Sec-Fetch-Dest" value="image"/>
    <header name="Sec-Fetch-Mode" value="no-cors"/>
    <header name="Sec-Fetch-Site" value="same-origin"/>
    <header name="User-Agent" value="Mozilla/5.0 (Windows NT 10.0; Win64; x64) AppleWebKit/537.36 (KHTML, like Gecko) Chrome/109.0.0.0 Safari/537.36"/>
    <responseHeaders>HTTP/1.1 200 OK&#xd;
Cache-Control: max-age=172800&#xd;
Content-Type: image/png&#xd;
Last-Modified: Wed, 24 Dec 2014 00:39:48 GMT&#xd;
Accept-Ranges: bytes&#xd;
ETag: "062c71e121fd01:0"&#xd;
Server: Microsoft-IIS/10.0&#xd;
X-Powered-By: ASP.NET&#xd;
Date: Mon, 27 Feb 2023 19:24:41 GMT&#xd;
Content-Length: 1185</responseHeaders>
    <record-html-infos extractorRegExp="false" htmlType="0"/>
</http-action>
<http-action actionType="1" contentType="image/png"
    eTag="&quot;02a952afd28d01:0&quot;" extractorInjectPathPolicy="2"
    extractorPathPolicy="1" followRedirects="false"
    generatedByClient="false"
    lastModified="Mon, 05 Jan 2015 15:35:00 GMT"
    linkExtractorSeveralMatchOccurrence="1"
    linkExtractorSeveralMatchPolicy="1" linkExtractorType="6"
    method="GET" name="/qaphr998/images/vision/reports.png"
    path="/qaphr998/images/vision/reports.png" postType="6"
    recordedArtifactZipFileName="team/vus/@prism@h@r_@payroll_@c4635756_@o@l@ds/%resources%/recorded-artifacts/340d258d-103b-43b9-838b-54f6a89ebdc7.zip"
    recordedResponseCode="200" responseSize="0"
    serverUid="imported_qaphr998.prismhr.com" slaProfileEnabled="false"
    uid="3c093a11-a3c2-478e-a62e-72f3af506bfe" useKeepAlive="false">
    <requestContentFileDescription>recorded-requests/req_089821f5-816b-40d1-b23c-01c0ddc1c767.txt</requestContentFileDescription>
    <header name="Accept" value="image/avif,image/webp,image/apng,image/svg+xml,image/*,*/*;q=0.8"/>
    <header name="Accept-Encoding" value="gzip, deflate, br"/>
    <header name="Accept-Language" value="en-US,en;q=0.9"/>
    <header name="Connection" value="keep-alive"/>
    <header name="Cookie" value="DesignBAIS=machine=BRGJRUIQQZBQESBROORAVVEEUDTAPPBTAZWMPIOOHUNGCOS&amp;pooler=537&amp;ver=40; IDBrowser=${IDBrowser}"/>
    <header name="Host" value="qaphr998.prismhr.com"/>
    <header name="Referer" value="https://qaphr998.prismhr.com/qaphr998/"/>
    <header name="sec-ch-ua" value="&quot;Not_A Brand&quot;;v=&quot;99&quot;, &quot;Google Chrome&quot;;v=&quot;109&quot;, &quot;Chromium&quot;;v=&quot;109&quot;"/>
    <header name="sec-ch-ua-mobile" value="?0"/>
    <header name="sec-ch-ua-platform" value="&quot;Windows&quot;"/>
    <header name="Sec-Fetch-Dest" value="image"/>
    <header name="Sec-Fetch-Mode" value="no-cors"/>
    <header name="Sec-Fetch-Site" value="same-origin"/>
    <header name="User-Agent" value="Mozilla/5.0 (Windows NT 10.0; Win64; x64) AppleWebKit/537.36 (KHTML, like Gecko) Chrome/109.0.0.0 Safari/537.36"/>
    <responseHeaders>HTTP/1.1 200 OK&#xd;
Cache-Control: max-age=172800&#xd;
Content-Type: image/png&#xd;
Last-Modified: Mon, 05 Jan 2015 15:35:00 GMT&#xd;
Accept-Ranges: bytes&#xd;
ETag: "02a952afd28d01:0"&#xd;
Server: Microsoft-IIS/10.0&#xd;
X-Powered-By: ASP.NET&#xd;
Date: Mon, 27 Feb 2023 19:24:41 GMT&#xd;
Content-Length: 1776</responseHeaders>
    <record-html-infos extractorRegExp="false" htmlType="0"/>
</http-action>
<http-action actionType="1" contentType="image/png"
    eTag="&quot;0a979fefc28d01:0&quot;" extractorInjectPathPolicy="2"
    extractorPathPolicy="1" followRedirects="false"
    generatedByClient="false"
    lastModified="Mon, 05 Jan 2015 15:33:46 GMT"
    linkExtractorSeveralMatchOccurrence="1"
    linkExtractorSeveralMatchPolicy="1" linkExtractorType="6"
    method="GET" name="/qaphr998/images/vision/bar_chart.png"
    path="/qaphr998/images/vision/bar_chart.png" postType="6"
    recordedArtifactZipFileName="team/vus/@prism@h@r_@payroll_@c4635756_@o@l@ds/%resources%/recorded-artifacts/340d258d-103b-43b9-838b-54f6a89ebdc7.zip"
    recordedResponseCode="200" responseSize="0"
    serverUid="imported_qaphr998.prismhr.com" slaProfileEnabled="false"
    uid="f6b897af-5237-4b98-a670-f2366b55ea0d" useKeepAlive="false">
    <requestContentFileDescription>recorded-requests/req_94c19235-34f8-489f-ab32-41e440a9acab.txt</requestContentFileDescription>
    <header name="Accept" value="image/avif,image/webp,image/apng,image/svg+xml,image/*,*/*;q=0.8"/>
    <header name="Accept-Encoding" value="gzip, deflate, br"/>
    <header name="Accept-Language" value="en-US,en;q=0.9"/>
    <header name="Connection" value="keep-alive"/>
    <header name="Cookie" value="DesignBAIS=machine=BRGJRUIQQZBQESBROORAVVEEUDTAPPBTAZWMPIOOHUNGCOS&amp;pooler=537&amp;ver=40; IDBrowser=${IDBrowser}"/>
    <header name="Host" value="qaphr998.prismhr.com"/>
    <header name="Referer" value="https://qaphr998.prismhr.com/qaphr998/"/>
    <header name="sec-ch-ua" value="&quot;Not_A Brand&quot;;v=&quot;99&quot;, &quot;Google Chrome&quot;;v=&quot;109&quot;, &quot;Chromium&quot;;v=&quot;109&quot;"/>
    <header name="sec-ch-ua-mobile" value="?0"/>
    <header name="sec-ch-ua-platform" value="&quot;Windows&quot;"/>
    <header name="Sec-Fetch-Dest" value="image"/>
    <header name="Sec-Fetch-Mode" value="no-cors"/>
    <header name="Sec-Fetch-Site" value="same-origin"/>
    <header name="User-Agent" value="Mozilla/5.0 (Windows NT 10.0; Win64; x64) AppleWebKit/537.36 (KHTML, like Gecko) Chrome/109.0.0.0 Safari/537.36"/>
    <responseHeaders>HTTP/1.1 200 OK&#xd;
Cache-Control: max-age=172800&#xd;
Content-Type: image/png&#xd;
Last-Modified: Mon, 05 Jan 2015 15:33:46 GMT&#xd;
Accept-Ranges: bytes&#xd;
ETag: "0a979fefc28d01:0"&#xd;
Server: Microsoft-IIS/10.0&#xd;
X-Powered-By: ASP.NET&#xd;
Date: Mon, 27 Feb 2023 19:24:41 GMT&#xd;
Content-Length: 6956</responseHeaders>
    <record-html-infos extractorRegExp="false" htmlType="0"/>
</http-action>
<http-action actionType="1" contentType="image/png"
    eTag="&quot;04e2840121fd01:0&quot;" extractorInjectPathPolicy="2"
    extractorPathPolicy="1" followRedirects="false"
    generatedByClient="false"
    lastModified="Wed, 24 Dec 2014 00:40:44 GMT"
    linkExtractorSeveralMatchOccurrence="1"
    linkExtractorSeveralMatchPolicy="1" linkExtractorType="6"
    method="GET" name="/qaphr998/images/vision/notes.png"
    path="/qaphr998/images/vision/notes.png" postType="6"
    recordedArtifactZipFileName="team/vus/@prism@h@r_@payroll_@c4635756_@o@l@ds/%resources%/recorded-artifacts/340d258d-103b-43b9-838b-54f6a89ebdc7.zip"
    recordedResponseCode="200" responseSize="0"
    serverUid="imported_qaphr998.prismhr.com" slaProfileEnabled="false"
    uid="d02675f1-e236-46d7-b999-e98419bfdbfd" useKeepAlive="false">
    <requestContentFileDescription>recorded-requests/req_2aed285b-db17-4cf2-9023-febb87d58399.txt</requestContentFileDescription>
    <header name="Accept" value="image/avif,image/webp,image/apng,image/svg+xml,image/*,*/*;q=0.8"/>
    <header name="Accept-Encoding" value="gzip, deflate, br"/>
    <header name="Accept-Language" value="en-US,en;q=0.9"/>
    <header name="Connection" value="keep-alive"/>
    <header name="Cookie" value="DesignBAIS=machine=BRGJRUIQQZBQESBROORAVVEEUDTAPPBTAZWMPIOOHUNGCOS&amp;pooler=537&amp;ver=40; IDBrowser=${IDBrowser}"/>
    <header name="Host" value="qaphr998.prismhr.com"/>
    <header name="Referer" value="https://qaphr998.prismhr.com/qaphr998/"/>
    <header name="sec-ch-ua" value="&quot;Not_A Brand&quot;;v=&quot;99&quot;, &quot;Google Chrome&quot;;v=&quot;109&quot;, &quot;Chromium&quot;;v=&quot;109&quot;"/>
    <header name="sec-ch-ua-mobile" value="?0"/>
    <header name="sec-ch-ua-platform" value="&quot;Windows&quot;"/>
    <header name="Sec-Fetch-Dest" value="image"/>
    <header name="Sec-Fetch-Mode" value="no-cors"/>
    <header name="Sec-Fetch-Site" value="same-origin"/>
    <header name="User-Agent" value="Mozilla/5.0 (Windows NT 10.0; Win64; x64) AppleWebKit/537.36 (KHTML, like Gecko) Chrome/109.0.0.0 Safari/537.36"/>
    <responseHeaders>HTTP/1.1 200 OK&#xd;
Cache-Control: max-age=172800&#xd;
Content-Type: image/png&#xd;
Last-Modified: Wed, 24 Dec 2014 00:40:44 GMT&#xd;
Accept-Ranges: bytes&#xd;
ETag: "04e2840121fd01:0"&#xd;
Server: Microsoft-IIS/10.0&#xd;
X-Powered-By: ASP.NET&#xd;
Date: Mon, 27 Feb 2023 19:24:41 GMT&#xd;
Content-Length: 1430</responseHeaders>
    <record-html-infos extractorRegExp="false" htmlType="0"/>
</http-action>
<http-action actionType="1" contentType="image/png"
    eTag="&quot;03d454d121fd01:0&quot;" extractorInjectPathPolicy="2"
    extractorPathPolicy="1" followRedirects="false"
    generatedByClient="false"
    lastModified="Wed, 24 Dec 2014 00:41:06 GMT"
    linkExtractorSeveralMatchOccurrence="1"
    linkExtractorSeveralMatchPolicy="1" linkExtractorType="6"
    method="GET" name="/qaphr998/images/vision/filteroff.png"
    path="/qaphr998/images/vision/filteroff.png" postType="6"
    recordedArtifactZipFileName="team/vus/@prism@h@r_@payroll_@c4635756_@o@l@ds/%resources%/recorded-artifacts/340d258d-103b-43b9-838b-54f6a89ebdc7.zip"
    recordedResponseCode="200" responseSize="0"
    serverUid="imported_qaphr998.prismhr.com" slaProfileEnabled="false"
    uid="8ac3f6b9-f90d-46ab-8183-be24ce0d00a4" useKeepAlive="false">
    <requestContentFileDescription>recorded-requests/req_e33b15de-4d2c-42f1-a8c1-c8e32b89309d.txt</requestContentFileDescription>
    <header name="Accept" value="image/avif,image/webp,image/apng,image/svg+xml,image/*,*/*;q=0.8"/>
    <header name="Accept-Encoding" value="gzip, deflate, br"/>
    <header name="Accept-Language" value="en-US,en;q=0.9"/>
    <header name="Connection" value="keep-alive"/>
    <header name="Cookie" value="DesignBAIS=machine=BRGJRUIQQZBQESBROORAVVEEUDTAPPBTAZWMPIOOHUNGCOS&amp;pooler=537&amp;ver=40; IDBrowser=${IDBrowser}"/>
    <header name="Host" value="qaphr998.prismhr.com"/>
    <header name="Referer" value="https://qaphr998.prismhr.com/qaphr998/"/>
    <header name="sec-ch-ua" value="&quot;Not_A Brand&quot;;v=&quot;99&quot;, &quot;Google Chrome&quot;;v=&quot;109&quot;, &quot;Chromium&quot;;v=&quot;109&quot;"/>
    <header name="sec-ch-ua-mobile" value="?0"/>
    <header name="sec-ch-ua-platform" value="&quot;Windows&quot;"/>
    <header name="Sec-Fetch-Dest" value="image"/>
    <header name="Sec-Fetch-Mode" value="no-cors"/>
    <header name="Sec-Fetch-Site" value="same-origin"/>
    <header name="User-Agent" value="Mozilla/5.0 (Windows NT 10.0; Win64; x64) AppleWebKit/537.36 (KHTML, like Gecko) Chrome/109.0.0.0 Safari/537.36"/>
    <responseHeaders>HTTP/1.1 200 OK&#xd;
Cache-Control: max-age=172800&#xd;
Content-Type: image/png&#xd;
Last-Modified: Wed, 24 Dec 2014 00:41:06 GMT&#xd;
Accept-Ranges: bytes&#xd;
ETag: "03d454d121fd01:0"&#xd;
Server: Microsoft-IIS/10.0&#xd;
X-Powered-By: ASP.NET&#xd;
Date: Mon, 27 Feb 2023 19:24:41 GMT&#xd;
Content-Length: 953</responseHeaders>
    <record-html-infos extractorRegExp="false" htmlType="0"/>
</http-action>
<http-action actionType="1" contentType="text/html" enabled="false"
    extractorInjectPathPolicy="2" extractorPathPolicy="1"
    followRedirects="false" generatedByClient="false"
    linkExtractorSeveralMatchOccurrence="1"
    linkExtractorSeveralMatchPolicy="1" linkExtractorType="6"
    method="GET" name="/qaphr998/images/blank.jpg"
    path="/qaphr998/images/blank.jpg" postType="6"
    recordedArtifactZipFileName="team/vus/@prism@h@r_@payroll_@c4635756_@o@l@ds/%resources%/recorded-artifacts/340d258d-103b-43b9-838b-54f6a89ebdc7.zip"
    recordedResponseCode="404" responseSize="1245"
    serverUid="imported_qaphr998.prismhr.com" slaProfileEnabled="false"
    uid="4af70c95-d23f-4e44-872b-29a27e2951fc" useKeepAlive="false">
    <responsePageFileDescription>recorded-responses/res_48667f5a-0c80-42cb-b52c-70066806dd9b.html</responsePageFileDescription>
    <requestContentFileDescription>recorded-requests/req_48667f5a-0c80-42cb-b52c-70066806dd9b.txt</requestContentFileDescription>
    <header name="Accept" value="image/avif,image/webp,image/apng,image/svg+xml,image/*,*/*;q=0.8"/>
    <header name="Accept-Encoding" value="gzip, deflate, br"/>
    <header name="Accept-Language" value="en-US,en;q=0.9"/>
    <header name="Connection" value="keep-alive"/>
    <header name="Cookie" value="DesignBAIS=machine=BRGJRUIQQZBQESBROORAVVEEUDTAPPBTAZWMPIOOHUNGCOS&amp;pooler=537&amp;ver=40; IDBrowser=${IDBrowser}"/>
    <header name="Host" value="qaphr998.prismhr.com"/>
    <header name="Referer" value="https://qaphr998.prismhr.com/qaphr998/"/>
    <header name="sec-ch-ua" value="&quot;Not_A Brand&quot;;v=&quot;99&quot;, &quot;Google Chrome&quot;;v=&quot;109&quot;, &quot;Chromium&quot;;v=&quot;109&quot;"/>
    <header name="sec-ch-ua-mobile" value="?0"/>
    <header name="sec-ch-ua-platform" value="&quot;Windows&quot;"/>
    <header name="Sec-Fetch-Dest" value="image"/>
    <header name="Sec-Fetch-Mode" value="no-cors"/>
    <header name="Sec-Fetch-Site" value="same-origin"/>
    <header name="User-Agent" value="Mozilla/5.0 (Windows NT 10.0; Win64; x64) AppleWebKit/537.36 (KHTML, like Gecko) Chrome/109.0.0.0 Safari/537.36"/>
    <responseHeaders>HTTP/1.1 404 Not Found&#xd;
Content-Type: text/html&#xd;
Server: Microsoft-IIS/10.0&#xd;
X-Powered-By: ASP.NET&#xd;
Date: Mon, 27 Feb 2023 19:24:41 GMT&#xd;
Content-Length: 1245</responseHeaders>
    <record-html-infos extractorRegExp="false" htmlType="0"/>
</http-action>
<http-action actionType="1" contentType="image/png"
    eTag="&quot;02032f31ca0ce1:0&quot;" extractorInjectPathPolicy="2"
    extractorPathPolicy="1" followRedirects="false"
    generatedByClient="false"
    lastModified="Fri, 23 Aug 2013 16:22:24 GMT"
    linkExtractorSeveralMatchOccurrence="1"
    linkExtractorSeveralMatchPolicy="1" linkExtractorType="6"
    method="GET" name="/qaphr998/images/vision/Arrow-down.png"
    path="/qaphr998/images/vision/Arrow-down.png" postType="6"
    recordedArtifactZipFileName="team/vus/@prism@h@r_@payroll_@c4635756_@o@l@ds/%resources%/recorded-artifacts/340d258d-103b-43b9-838b-54f6a89ebdc7.zip"
    recordedResponseCode="200" responseSize="0"
    serverUid="imported_qaphr998.prismhr.com" slaProfileEnabled="false"
    uid="92268e1c-df76-469f-9ec3-b085fa6d4739" useKeepAlive="false">
    <requestContentFileDescription>recorded-requests/req_2ff5ae48-bc73-4c15-9f26-7ce16fc7bd0b.txt</requestContentFileDescription>
    <header name="Accept" value="image/avif,image/webp,image/apng,image/svg+xml,image/*,*/*;q=0.8"/>
    <header name="Accept-Encoding" value="gzip, deflate, br"/>
    <header name="Accept-Language" value="en-US,en;q=0.9"/>
    <header name="Connection" value="keep-alive"/>
    <header name="Cookie" value="DesignBAIS=machine=BRGJRUIQQZBQESBROORAVVEEUDTAPPBTAZWMPIOOHUNGCOS&amp;pooler=537&amp;ver=40; IDBrowser=${IDBrowser}"/>
    <header name="Host" value="qaphr998.prismhr.com"/>
    <header name="Referer" value="https://qaphr998.prismhr.com/qaphr998/"/>
    <header name="sec-ch-ua" value="&quot;Not_A Brand&quot;;v=&quot;99&quot;, &quot;Google Chrome&quot;;v=&quot;109&quot;, &quot;Chromium&quot;;v=&quot;109&quot;"/>
    <header name="sec-ch-ua-mobile" value="?0"/>
    <header name="sec-ch-ua-platform" value="&quot;Windows&quot;"/>
    <header name="Sec-Fetch-Dest" value="image"/>
    <header name="Sec-Fetch-Mode" value="no-cors"/>
    <header name="Sec-Fetch-Site" value="same-origin"/>
    <header name="User-Agent" value="Mozilla/5.0 (Windows NT 10.0; Win64; x64) AppleWebKit/537.36 (KHTML, like Gecko) Chrome/109.0.0.0 Safari/537.36"/>
    <responseHeaders>HTTP/1.1 200 OK&#xd;
Cache-Control: max-age=172800&#xd;
Content-Type: image/png&#xd;
Last-Modified: Fri, 23 Aug 2013 16:22:24 GMT&#xd;
Accept-Ranges: bytes&#xd;
ETag: "02032f31ca0ce1:0"&#xd;
Server: Microsoft-IIS/10.0&#xd;
X-Powered-By: ASP.NET&#xd;
Date: Mon, 27 Feb 2023 19:24:41 GMT&#xd;
Content-Length: 1138</responseHeaders>
    <record-html-infos extractorRegExp="false" htmlType="0"/>
</http-action>
<http-action actionType="1" contentType="image/png"
    eTag="&quot;08ed0959ded11:0&quot;" extractorInjectPathPolicy="2"
    extractorPathPolicy="1" followRedirects="false"
    generatedByClient="false"
    lastModified="Thu, 14 Jul 2016 19:54:52 GMT"
    linkExtractorSeveralMatchOccurrence="1"
    linkExtractorSeveralMatchPolicy="1" linkExtractorType="6"
    method="GET" name="/qaphr998/images/vision/PagePrevNew.png"
    path="/qaphr998/images/vision/PagePrevNew.png" postType="6"
    recordedArtifactZipFileName="team/vus/@prism@h@r_@payroll_@c4635756_@o@l@ds/%resources%/recorded-artifacts/340d258d-103b-43b9-838b-54f6a89ebdc7.zip"
    recordedResponseCode="200" responseSize="0"
    serverUid="imported_qaphr998.prismhr.com" slaProfileEnabled="false"
    uid="86279270-5043-492b-956b-928f42f8fe60" useKeepAlive="false">
    <requestContentFileDescription>recorded-requests/req_305339d6-59ea-41fb-9fef-04342b586210.txt</requestContentFileDescription>
    <header name="Accept" value="image/avif,image/webp,image/apng,image/svg+xml,image/*,*/*;q=0.8"/>
    <header name="Accept-Encoding" value="gzip, deflate, br"/>
    <header name="Accept-Language" value="en-US,en;q=0.9"/>
    <header name="Connection" value="keep-alive"/>
    <header name="Cookie" value="DesignBAIS=machine=BRGJRUIQQZBQESBROORAVVEEUDTAPPBTAZWMPIOOHUNGCOS&amp;pooler=537&amp;ver=40; IDBrowser=${IDBrowser}"/>
    <header name="Host" value="qaphr998.prismhr.com"/>
    <header name="Referer" value="https://qaphr998.prismhr.com/qaphr998/"/>
    <header name="sec-ch-ua" value="&quot;Not_A Brand&quot;;v=&quot;99&quot;, &quot;Google Chrome&quot;;v=&quot;109&quot;, &quot;Chromium&quot;;v=&quot;109&quot;"/>
    <header name="sec-ch-ua-mobile" value="?0"/>
    <header name="sec-ch-ua-platform" value="&quot;Windows&quot;"/>
    <header name="Sec-Fetch-Dest" value="image"/>
    <header name="Sec-Fetch-Mode" value="no-cors"/>
    <header name="Sec-Fetch-Site" value="same-origin"/>
    <header name="User-Agent" value="Mozilla/5.0 (Windows NT 10.0; Win64; x64) AppleWebKit/537.36 (KHTML, like Gecko) Chrome/109.0.0.0 Safari/537.36"/>
    <responseHeaders>HTTP/1.1 200 OK&#xd;
Cache-Control: max-age=172800&#xd;
Content-Type: image/png&#xd;
Last-Modified: Thu, 14 Jul 2016 19:54:52 GMT&#xd;
Accept-Ranges: bytes&#xd;
ETag: "08ed0959ded11:0"&#xd;
Server: Microsoft-IIS/10.0&#xd;
X-Powered-By: ASP.NET&#xd;
Date: Mon, 27 Feb 2023 19:24:41 GMT&#xd;
Content-Length: 1394</responseHeaders>
    <record-html-infos extractorRegExp="false" htmlType="0"/>
</http-action>
<http-action actionType="1" contentType="image/png"
    eTag="&quot;0c66cb29ded11:0&quot;" extractorInjectPathPolicy="2"
    extractorPathPolicy="1" followRedirects="false"
    generatedByClient="false"
    lastModified="Thu, 14 Jul 2016 19:55:40 GMT"
    linkExtractorSeveralMatchOccurrence="1"
    linkExtractorSeveralMatchPolicy="1" linkExtractorType="6"
    method="GET" name="/qaphr998/images/vision/PageNew.png"
    path="/qaphr998/images/vision/PageNew.png" postType="6"
    recordedArtifactZipFileName="team/vus/@prism@h@r_@payroll_@c4635756_@o@l@ds/%resources%/recorded-artifacts/340d258d-103b-43b9-838b-54f6a89ebdc7.zip"
    recordedResponseCode="200" responseSize="0"
    serverUid="imported_qaphr998.prismhr.com" slaProfileEnabled="false"
    uid="d46fbaa0-5cb8-44c7-9c65-e3eebb6ec46c" useKeepAlive="false">
    <requestContentFileDescription>recorded-requests/req_9bf5a912-e2a9-44b7-8d21-d05e8ab7abbf.txt</requestContentFileDescription>
    <header name="Accept" value="image/avif,image/webp,image/apng,image/svg+xml,image/*,*/*;q=0.8"/>
    <header name="Accept-Encoding" value="gzip, deflate, br"/>
    <header name="Accept-Language" value="en-US,en;q=0.9"/>
    <header name="Connection" value="keep-alive"/>
    <header name="Cookie" value="DesignBAIS=machine=BRGJRUIQQZBQESBROORAVVEEUDTAPPBTAZWMPIOOHUNGCOS&amp;pooler=537&amp;ver=40; IDBrowser=${IDBrowser}"/>
    <header name="Host" value="qaphr998.prismhr.com"/>
    <header name="Referer" value="https://qaphr998.prismhr.com/qaphr998/"/>
    <header name="sec-ch-ua" value="&quot;Not_A Brand&quot;;v=&quot;99&quot;, &quot;Google Chrome&quot;;v=&quot;109&quot;, &quot;Chromium&quot;;v=&quot;109&quot;"/>
    <header name="sec-ch-ua-mobile" value="?0"/>
    <header name="sec-ch-ua-platform" value="&quot;Windows&quot;"/>
    <header name="Sec-Fetch-Dest" value="image"/>
    <header name="Sec-Fetch-Mode" value="no-cors"/>
    <header name="Sec-Fetch-Site" value="same-origin"/>
    <header name="User-Agent" value="Mozilla/5.0 (Windows NT 10.0; Win64; x64) AppleWebKit/537.36 (KHTML, like Gecko) Chrome/109.0.0.0 Safari/537.36"/>
    <responseHeaders>HTTP/1.1 200 OK&#xd;
Cache-Control: max-age=172800&#xd;
Content-Type: image/png&#xd;
Last-Modified: Thu, 14 Jul 2016 19:55:40 GMT&#xd;
Accept-Ranges: bytes&#xd;
ETag: "0c66cb29ded11:0"&#xd;
Server: Microsoft-IIS/10.0&#xd;
X-Powered-By: ASP.NET&#xd;
Date: Mon, 27 Feb 2023 19:24:41 GMT&#xd;
Content-Length: 1575</responseHeaders>
    <record-html-infos extractorRegExp="false" htmlType="0"/>
</http-action>
<http-action actionType="1" contentType="image/png"
    eTag="&quot;05f161aa0ce1:0&quot;" extractorInjectPathPolicy="2"
    extractorPathPolicy="1" followRedirects="false"
    generatedByClient="false"
    lastModified="Fri, 23 Aug 2013 16:01:54 GMT"
    linkExtractorSeveralMatchOccurrence="1"
    linkExtractorSeveralMatchPolicy="1" linkExtractorType="6"
    method="GET" name="/qaphr998/images/vision/Close_btn_09mo.png"
    path="/qaphr998/images/vision/Close_btn_09mo.png" postType="6"
    recordedArtifactZipFileName="team/vus/@prism@h@r_@payroll_@c4635756_@o@l@ds/%resources%/recorded-artifacts/340d258d-103b-43b9-838b-54f6a89ebdc7.zip"
    recordedResponseCode="200" responseSize="0"
    serverUid="imported_qaphr998.prismhr.com" slaProfileEnabled="false"
    uid="3424114e-b66a-47f1-9527-d8266a10dbc9" useKeepAlive="false">
    <requestContentFileDescription>recorded-requests/req_fbf85e3a-ba7c-4fc2-a924-05c17de05a14.txt</requestContentFileDescription>
    <header name="Accept" value="image/avif,image/webp,image/apng,image/svg+xml,image/*,*/*;q=0.8"/>
    <header name="Accept-Encoding" value="gzip, deflate, br"/>
    <header name="Accept-Language" value="en-US,en;q=0.9"/>
    <header name="Connection" value="keep-alive"/>
    <header name="Cookie" value="DesignBAIS=machine=BRGJRUIQQZBQESBROORAVVEEUDTAPPBTAZWMPIOOHUNGCOS&amp;pooler=537&amp;ver=40; IDBrowser=${IDBrowser}"/>
    <header name="Host" value="qaphr998.prismhr.com"/>
    <header name="Referer" value="https://qaphr998.prismhr.com/qaphr998/"/>
    <header name="sec-ch-ua" value="&quot;Not_A Brand&quot;;v=&quot;99&quot;, &quot;Google Chrome&quot;;v=&quot;109&quot;, &quot;Chromium&quot;;v=&quot;109&quot;"/>
    <header name="sec-ch-ua-mobile" value="?0"/>
    <header name="sec-ch-ua-platform" value="&quot;Windows&quot;"/>
    <header name="Sec-Fetch-Dest" value="image"/>
    <header name="Sec-Fetch-Mode" value="no-cors"/>
    <header name="Sec-Fetch-Site" value="same-origin"/>
    <header name="User-Agent" value="Mozilla/5.0 (Windows NT 10.0; Win64; x64) AppleWebKit/537.36 (KHTML, like Gecko) Chrome/109.0.0.0 Safari/537.36"/>
    <responseHeaders>HTTP/1.1 200 OK&#xd;
Cache-Control: max-age=172800&#xd;
Content-Type: image/png&#xd;
Last-Modified: Fri, 23 Aug 2013 16:01:54 GMT&#xd;
Accept-Ranges: bytes&#xd;
ETag: "05f161aa0ce1:0"&#xd;
Server: Microsoft-IIS/10.0&#xd;
X-Powered-By: ASP.NET&#xd;
Date: Mon, 27 Feb 2023 19:24:41 GMT&#xd;
Content-Length: 2902</responseHeaders>
    <record-html-infos extractorRegExp="false" htmlType="0"/>
</http-action>
<http-action actionType="1" contentType="image/png"
    eTag="&quot;02032f31ca0ce1:0&quot;" extractorInjectPathPolicy="2"
    extractorPathPolicy="1" followRedirects="false"
    generatedByClient="false"
    lastModified="Fri, 23 Aug 2013 16:22:24 GMT"
    linkExtractorSeveralMatchOccurrence="1"
    linkExtractorSeveralMatchPolicy="1" linkExtractorType="6"
    method="GET" name="/qaphr998/images/vision/Arrow-up.png"
    path="/qaphr998/images/vision/Arrow-up.png" postType="6"
    recordedArtifactZipFileName="team/vus/@prism@h@r_@payroll_@c4635756_@o@l@ds/%resources%/recorded-artifacts/340d258d-103b-43b9-838b-54f6a89ebdc7.zip"
    recordedResponseCode="200" responseSize="0"
    serverUid="imported_qaphr998.prismhr.com" slaProfileEnabled="false"
    uid="178bab4d-2975-489b-8040-6c527151eb29" useKeepAlive="false">
    <requestContentFileDescription>recorded-requests/req_b8c84670-c23b-4544-b9bd-200d5de5166f.txt</requestContentFileDescription>
    <header name="Accept" value="image/avif,image/webp,image/apng,image/svg+xml,image/*,*/*;q=0.8"/>
    <header name="Accept-Encoding" value="gzip, deflate, br"/>
    <header name="Accept-Language" value="en-US,en;q=0.9"/>
    <header name="Connection" value="keep-alive"/>
    <header name="Cookie" value="DesignBAIS=machine=BRGJRUIQQZBQESBROORAVVEEUDTAPPBTAZWMPIOOHUNGCOS&amp;pooler=537&amp;ver=40; IDBrowser=${IDBrowser}"/>
    <header name="Host" value="qaphr998.prismhr.com"/>
    <header name="Referer" value="https://qaphr998.prismhr.com/qaphr998/"/>
    <header name="sec-ch-ua" value="&quot;Not_A Brand&quot;;v=&quot;99&quot;, &quot;Google Chrome&quot;;v=&quot;109&quot;, &quot;Chromium&quot;;v=&quot;109&quot;"/>
    <header name="sec-ch-ua-mobile" value="?0"/>
    <header name="sec-ch-ua-platform" value="&quot;Windows&quot;"/>
    <header name="Sec-Fetch-Dest" value="image"/>
    <header name="Sec-Fetch-Mode" value="no-cors"/>
    <header name="Sec-Fetch-Site" value="same-origin"/>
    <header name="User-Agent" value="Mozilla/5.0 (Windows NT 10.0; Win64; x64) AppleWebKit/537.36 (KHTML, like Gecko) Chrome/109.0.0.0 Safari/537.36"/>
    <responseHeaders>HTTP/1.1 200 OK&#xd;
Cache-Control: max-age=172800&#xd;
Content-Type: image/png&#xd;
Last-Modified: Fri, 23 Aug 2013 16:22:24 GMT&#xd;
Accept-Ranges: bytes&#xd;
ETag: "02032f31ca0ce1:0"&#xd;
Server: Microsoft-IIS/10.0&#xd;
X-Powered-By: ASP.NET&#xd;
Date: Mon, 27 Feb 2023 19:24:41 GMT&#xd;
Content-Length: 1117</responseHeaders>
    <record-html-infos extractorRegExp="false" htmlType="0"/>
</http-action>
<http-action actionType="1" contentType="image/png"
    eTag="&quot;e82e628b6e44d81:0&quot;" extractorInjectPathPolicy="2"
    extractorPathPolicy="1" followRedirects="false"
    generatedByClient="false"
    lastModified="Wed, 30 Mar 2022 19:44:18 GMT"
    linkExtractorSeveralMatchOccurrence="1"
    linkExtractorSeveralMatchPolicy="1" linkExtractorType="6"
    method="GET" name="/qaphr998/images/Close_btn_09.png"
    path="/qaphr998/images/Close_btn_09.png" postType="6"
    recordedArtifactZipFileName="team/vus/@prism@h@r_@payroll_@c4635756_@o@l@ds/%resources%/recorded-artifacts/340d258d-103b-43b9-838b-54f6a89ebdc7.zip"
    recordedResponseCode="200" responseSize="0"
    serverUid="imported_qaphr998.prismhr.com" slaProfileEnabled="false"
    uid="d37668ff-adc4-4df5-b310-ccc3f453076f" useKeepAlive="false">
    <requestContentFileDescription>recorded-requests/req_7d606e38-b329-4f25-9427-bf6e496fb0fa.txt</requestContentFileDescription>
    <header name="Accept" value="image/avif,image/webp,image/apng,image/svg+xml,image/*,*/*;q=0.8"/>
    <header name="Accept-Encoding" value="gzip, deflate, br"/>
    <header name="Accept-Language" value="en-US,en;q=0.9"/>
    <header name="Connection" value="keep-alive"/>
    <header name="Cookie" value="DesignBAIS=machine=BRGJRUIQQZBQESBROORAVVEEUDTAPPBTAZWMPIOOHUNGCOS&amp;pooler=537&amp;ver=40; IDBrowser=${IDBrowser}"/>
    <header name="Host" value="qaphr998.prismhr.com"/>
    <header name="Referer" value="https://qaphr998.prismhr.com/qaphr998/"/>
    <header name="sec-ch-ua" value="&quot;Not_A Brand&quot;;v=&quot;99&quot;, &quot;Google Chrome&quot;;v=&quot;109&quot;, &quot;Chromium&quot;;v=&quot;109&quot;"/>
    <header name="sec-ch-ua-mobile" value="?0"/>
    <header name="sec-ch-ua-platform" value="&quot;Windows&quot;"/>
    <header name="Sec-Fetch-Dest" value="image"/>
    <header name="Sec-Fetch-Mode" value="no-cors"/>
    <header name="Sec-Fetch-Site" value="same-origin"/>
    <header name="User-Agent" value="Mozilla/5.0 (Windows NT 10.0; Win64; x64) AppleWebKit/537.36 (KHTML, like Gecko) Chrome/109.0.0.0 Safari/537.36"/>
    <responseHeaders>HTTP/1.1 200 OK&#xd;
Cache-Control: max-age=172800&#xd;
Content-Type: image/png&#xd;
Last-Modified: Wed, 30 Mar 2022 19:44:18 GMT&#xd;
Accept-Ranges: bytes&#xd;
ETag: "e82e628b6e44d81:0"&#xd;
Server: Microsoft-IIS/10.0&#xd;
X-Powered-By: ASP.NET&#xd;
Date: Mon, 27 Feb 2023 19:24:41 GMT&#xd;
Content-Length: 3713</responseHeaders>
    <record-html-infos extractorRegExp="false" htmlType="0"/>
</http-action>
<http-action actionType="1" contentType="image/png"
    eTag="&quot;0de86177f19d01:0&quot;" extractorInjectPathPolicy="2"
    extractorPathPolicy="1" followRedirects="false"
    generatedByClient="false"
    lastModified="Tue, 16 Dec 2014 22:24:44 GMT"
    linkExtractorSeveralMatchOccurrence="1"
    linkExtractorSeveralMatchPolicy="1" linkExtractorType="6"
    method="GET" name="/qaphr998/images/vision/Checkboxoff14.png"
    path="/qaphr998/images/vision/Checkboxoff14.png" postType="6"
    recordedArtifactZipFileName="team/vus/@prism@h@r_@payroll_@c4635756_@o@l@ds/%resources%/recorded-artifacts/340d258d-103b-43b9-838b-54f6a89ebdc7.zip"
    recordedResponseCode="200" responseSize="0"
    serverUid="imported_qaphr998.prismhr.com" slaProfileEnabled="false"
    uid="06a2253c-67c5-43ab-bbd6-c7187894ddb6" useKeepAlive="false">
    <requestContentFileDescription>recorded-requests/req_21adabd0-ae4f-4db8-96de-529f69787052.txt</requestContentFileDescription>
    <header name="Accept" value="image/avif,image/webp,image/apng,image/svg+xml,image/*,*/*;q=0.8"/>
    <header name="Accept-Encoding" value="gzip, deflate, br"/>
    <header name="Accept-Language" value="en-US,en;q=0.9"/>
    <header name="Connection" value="keep-alive"/>
    <header name="Cookie" value="DesignBAIS=machine=BRGJRUIQQZBQESBROORAVVEEUDTAPPBTAZWMPIOOHUNGCOS&amp;pooler=537&amp;ver=40; IDBrowser=${IDBrowser}"/>
    <header name="Host" value="qaphr998.prismhr.com"/>
    <header name="Referer" value="https://qaphr998.prismhr.com/qaphr998/"/>
    <header name="sec-ch-ua" value="&quot;Not_A Brand&quot;;v=&quot;99&quot;, &quot;Google Chrome&quot;;v=&quot;109&quot;, &quot;Chromium&quot;;v=&quot;109&quot;"/>
    <header name="sec-ch-ua-mobile" value="?0"/>
    <header name="sec-ch-ua-platform" value="&quot;Windows&quot;"/>
    <header name="Sec-Fetch-Dest" value="image"/>
    <header name="Sec-Fetch-Mode" value="no-cors"/>
    <header name="Sec-Fetch-Site" value="same-origin"/>
    <header name="User-Agent" value="Mozilla/5.0 (Windows NT 10.0; Win64; x64) AppleWebKit/537.36 (KHTML, like Gecko) Chrome/109.0.0.0 Safari/537.36"/>
    <responseHeaders>HTTP/1.1 200 OK&#xd;
Cache-Control: max-age=172800&#xd;
Content-Type: image/png&#xd;
Last-Modified: Tue, 16 Dec 2014 22:24:44 GMT&#xd;
Accept-Ranges: bytes&#xd;
ETag: "0de86177f19d01:0"&#xd;
Server: Microsoft-IIS/10.0&#xd;
X-Powered-By: ASP.NET&#xd;
Date: Mon, 27 Feb 2023 19:24:41 GMT&#xd;
Content-Length: 485</responseHeaders>
    <record-html-infos extractorRegExp="false" htmlType="0"/>
</http-action>
<http-action actionType="1" contentType="image/png"
    eTag="&quot;073143afd28d01:0&quot;" extractorInjectPathPolicy="2"
    extractorPathPolicy="1" followRedirects="false"
    generatedByClient="false"
    lastModified="Mon, 05 Jan 2015 15:35:26 GMT"
    linkExtractorSeveralMatchOccurrence="1"
    linkExtractorSeveralMatchPolicy="1" linkExtractorType="6"
    method="GET" name="/qaphr998/images/vision/user.png"
    path="/qaphr998/images/vision/user.png" postType="6"
    recordedArtifactZipFileName="team/vus/@prism@h@r_@payroll_@c4635756_@o@l@ds/%resources%/recorded-artifacts/340d258d-103b-43b9-838b-54f6a89ebdc7.zip"
    recordedResponseCode="200" responseSize="0"
    serverUid="imported_qaphr998.prismhr.com" slaProfileEnabled="false"
    uid="89d4f531-ff81-4ec5-9908-6ff1da3e34cc" useKeepAlive="false">
    <requestContentFileDescription>recorded-requests/req_3a7e5cda-7b0d-47b2-a919-5b376b48969c.txt</requestContentFileDescription>
    <header name="Accept" value="image/avif,image/webp,image/apng,image/svg+xml,image/*,*/*;q=0.8"/>
    <header name="Accept-Encoding" value="gzip, deflate, br"/>
    <header name="Accept-Language" value="en-US,en;q=0.9"/>
    <header name="Connection" value="keep-alive"/>
    <header name="Cookie" value="DesignBAIS=machine=BRGJRUIQQZBQESBROORAVVEEUDTAPPBTAZWMPIOOHUNGCOS&amp;pooler=537&amp;ver=40; IDBrowser=${IDBrowser}"/>
    <header name="Host" value="qaphr998.prismhr.com"/>
    <header name="Referer" value="https://qaphr998.prismhr.com/qaphr998/"/>
    <header name="sec-ch-ua" value="&quot;Not_A Brand&quot;;v=&quot;99&quot;, &quot;Google Chrome&quot;;v=&quot;109&quot;, &quot;Chromium&quot;;v=&quot;109&quot;"/>
    <header name="sec-ch-ua-mobile" value="?0"/>
    <header name="sec-ch-ua-platform" value="&quot;Windows&quot;"/>
    <header name="Sec-Fetch-Dest" value="image"/>
    <header name="Sec-Fetch-Mode" value="no-cors"/>
    <header name="Sec-Fetch-Site" value="same-origin"/>
    <header name="User-Agent" value="Mozilla/5.0 (Windows NT 10.0; Win64; x64) AppleWebKit/537.36 (KHTML, like Gecko) Chrome/109.0.0.0 Safari/537.36"/>
    <responseHeaders>HTTP/1.1 200 OK&#xd;
Cache-Control: max-age=172800&#xd;
Content-Type: image/png&#xd;
Last-Modified: Mon, 05 Jan 2015 15:35:26 GMT&#xd;
Accept-Ranges: bytes&#xd;
ETag: "073143afd28d01:0"&#xd;
Server: Microsoft-IIS/10.0&#xd;
X-Powered-By: ASP.NET&#xd;
Date: Mon, 27 Feb 2023 19:24:41 GMT&#xd;
Content-Length: 3034</responseHeaders>
    <record-html-infos extractorRegExp="false" htmlType="0"/>
</http-action>
<http-action actionType="1" contentType="image/png"
    eTag="&quot;09fb3889ded11:0&quot;" extractorInjectPathPolicy="2"
    extractorPathPolicy="1" followRedirects="false"
    generatedByClient="false"
    lastModified="Thu, 14 Jul 2016 19:54:30 GMT"
    linkExtractorSeveralMatchOccurrence="1"
    linkExtractorSeveralMatchPolicy="1" linkExtractorType="6"
    method="GET" name="/qaphr998/images/vision/PageNextNew.png"
    path="/qaphr998/images/vision/PageNextNew.png" postType="6"
    recordedArtifactZipFileName="team/vus/@prism@h@r_@payroll_@c4635756_@o@l@ds/%resources%/recorded-artifacts/340d258d-103b-43b9-838b-54f6a89ebdc7.zip"
    recordedResponseCode="200" responseSize="0"
    serverUid="imported_qaphr998.prismhr.com" slaProfileEnabled="false"
    uid="787a7f7c-7495-45d3-bab7-39b3aeb6b3f9" useKeepAlive="false">
    <requestContentFileDescription>recorded-requests/req_1783d9ab-a9cb-45de-9e51-4d6b675d5af6.txt</requestContentFileDescription>
    <header name="Accept" value="image/avif,image/webp,image/apng,image/svg+xml,image/*,*/*;q=0.8"/>
    <header name="Accept-Encoding" value="gzip, deflate, br"/>
    <header name="Accept-Language" value="en-US,en;q=0.9"/>
    <header name="Connection" value="keep-alive"/>
    <header name="Cookie" value="DesignBAIS=machine=BRGJRUIQQZBQESBROORAVVEEUDTAPPBTAZWMPIOOHUNGCOS&amp;pooler=537&amp;ver=40; IDBrowser=${IDBrowser}"/>
    <header name="Host" value="qaphr998.prismhr.com"/>
    <header name="Referer" value="https://qaphr998.prismhr.com/qaphr998/"/>
    <header name="sec-ch-ua" value="&quot;Not_A Brand&quot;;v=&quot;99&quot;, &quot;Google Chrome&quot;;v=&quot;109&quot;, &quot;Chromium&quot;;v=&quot;109&quot;"/>
    <header name="sec-ch-ua-mobile" value="?0"/>
    <header name="sec-ch-ua-platform" value="&quot;Windows&quot;"/>
    <header name="Sec-Fetch-Dest" value="image"/>
    <header name="Sec-Fetch-Mode" value="no-cors"/>
    <header name="Sec-Fetch-Site" value="same-origin"/>
    <header name="User-Agent" value="Mozilla/5.0 (Windows NT 10.0; Win64; x64) AppleWebKit/537.36 (KHTML, like Gecko) Chrome/109.0.0.0 Safari/537.36"/>
    <responseHeaders>HTTP/1.1 200 OK&#xd;
Cache-Control: max-age=172800&#xd;
Content-Type: image/png&#xd;
Last-Modified: Thu, 14 Jul 2016 19:54:30 GMT&#xd;
Accept-Ranges: bytes&#xd;
ETag: "09fb3889ded11:0"&#xd;
Server: Microsoft-IIS/10.0&#xd;
X-Powered-By: ASP.NET&#xd;
Date: Mon, 27 Feb 2023 19:24:41 GMT&#xd;
Content-Length: 1259</responseHeaders>
    <record-html-infos extractorRegExp="false" htmlType="0"/>
</http-action>
<http-action actionType="1" contentType="image/png"
    eTag="&quot;0e13cbe23c1ce1:0&quot;" extractorInjectPathPolicy="2"
    extractorPathPolicy="1" followRedirects="false"
    generatedByClient="false"
    lastModified="Fri, 04 Oct 2013 17:04:10 GMT"
    linkExtractorSeveralMatchOccurrence="1"
    linkExtractorSeveralMatchPolicy="1" linkExtractorType="6"
    method="GET" name="/qaphr998/images/vision/notessmall.png"
    path="/qaphr998/images/vision/notessmall.png" postType="6"
    recordedArtifactZipFileName="team/vus/@prism@h@r_@payroll_@c4635756_@o@l@ds/%resources%/recorded-artifacts/340d258d-103b-43b9-838b-54f6a89ebdc7.zip"
    recordedResponseCode="200" responseSize="0"
    serverUid="imported_qaphr998.prismhr.com" slaProfileEnabled="false"
    uid="e49e57d1-454a-4912-a169-1a9e8b2e8a58" useKeepAlive="false">
    <requestContentFileDescription>recorded-requests/req_1d2d92e6-53cb-4ea8-97e8-619c16053506.txt</requestContentFileDescription>
    <header name="Accept" value="image/avif,image/webp,image/apng,image/svg+xml,image/*,*/*;q=0.8"/>
    <header name="Accept-Encoding" value="gzip, deflate, br"/>
    <header name="Accept-Language" value="en-US,en;q=0.9"/>
    <header name="Connection" value="keep-alive"/>
    <header name="Cookie" value="DesignBAIS=machine=BRGJRUIQQZBQESBROORAVVEEUDTAPPBTAZWMPIOOHUNGCOS&amp;pooler=537&amp;ver=40; IDBrowser=${IDBrowser}"/>
    <header name="Host" value="qaphr998.prismhr.com"/>
    <header name="Referer" value="https://qaphr998.prismhr.com/qaphr998/"/>
    <header name="sec-ch-ua" value="&quot;Not_A Brand&quot;;v=&quot;99&quot;, &quot;Google Chrome&quot;;v=&quot;109&quot;, &quot;Chromium&quot;;v=&quot;109&quot;"/>
    <header name="sec-ch-ua-mobile" value="?0"/>
    <header name="sec-ch-ua-platform" value="&quot;Windows&quot;"/>
    <header name="Sec-Fetch-Dest" value="image"/>
    <header name="Sec-Fetch-Mode" value="no-cors"/>
    <header name="Sec-Fetch-Site" value="same-origin"/>
    <header name="User-Agent" value="Mozilla/5.0 (Windows NT 10.0; Win64; x64) AppleWebKit/537.36 (KHTML, like Gecko) Chrome/109.0.0.0 Safari/537.36"/>
    <responseHeaders>HTTP/1.1 200 OK&#xd;
Cache-Control: max-age=172800&#xd;
Content-Type: image/png&#xd;
Last-Modified: Fri, 04 Oct 2013 17:04:10 GMT&#xd;
Accept-Ranges: bytes&#xd;
ETag: "0e13cbe23c1ce1:0"&#xd;
Server: Microsoft-IIS/10.0&#xd;
X-Powered-By: ASP.NET&#xd;
Date: Mon, 27 Feb 2023 19:24:41 GMT&#xd;
Content-Length: 658</responseHeaders>
    <record-html-infos extractorRegExp="false" htmlType="0"/>
</http-action>
<http-action actionType="1" contentType="image/png"
    eTag="&quot;08e588063b5ce1:0&quot;" extractorInjectPathPolicy="2"
    extractorPathPolicy="1" followRedirects="false"
    generatedByClient="false"
    lastModified="Thu, 19 Sep 2013 18:10:20 GMT"
    linkExtractorSeveralMatchOccurrence="1"
    linkExtractorSeveralMatchPolicy="1" linkExtractorType="6"
    method="GET" name="/qaphr998/images/vision/lockUnlocked.png"
    path="/qaphr998/images/vision/lockUnlocked.png" postType="6"
    recordedArtifactZipFileName="team/vus/@prism@h@r_@payroll_@c4635756_@o@l@ds/%resources%/recorded-artifacts/340d258d-103b-43b9-838b-54f6a89ebdc7.zip"
    recordedResponseCode="200" responseSize="0"
    serverUid="imported_qaphr998.prismhr.com" slaProfileEnabled="false"
    uid="00ecd9c7-6240-48a2-83dd-22112e1a60ec" useKeepAlive="false">
    <requestContentFileDescription>recorded-requests/req_0aef0243-b147-45a9-bf15-0089cfe14a4e.txt</requestContentFileDescription>
    <header name="Accept" value="image/avif,image/webp,image/apng,image/svg+xml,image/*,*/*;q=0.8"/>
    <header name="Accept-Encoding" value="gzip, deflate, br"/>
    <header name="Accept-Language" value="en-US,en;q=0.9"/>
    <header name="Connection" value="keep-alive"/>
    <header name="Cookie" value="DesignBAIS=machine=BRGJRUIQQZBQESBROORAVVEEUDTAPPBTAZWMPIOOHUNGCOS&amp;pooler=537&amp;ver=40; IDBrowser=${IDBrowser}"/>
    <header name="Host" value="qaphr998.prismhr.com"/>
    <header name="Referer" value="https://qaphr998.prismhr.com/qaphr998/"/>
    <header name="sec-ch-ua" value="&quot;Not_A Brand&quot;;v=&quot;99&quot;, &quot;Google Chrome&quot;;v=&quot;109&quot;, &quot;Chromium&quot;;v=&quot;109&quot;"/>
    <header name="sec-ch-ua-mobile" value="?0"/>
    <header name="sec-ch-ua-platform" value="&quot;Windows&quot;"/>
    <header name="Sec-Fetch-Dest" value="image"/>
    <header name="Sec-Fetch-Mode" value="no-cors"/>
    <header name="Sec-Fetch-Site" value="same-origin"/>
    <header name="User-Agent" value="Mozilla/5.0 (Windows NT 10.0; Win64; x64) AppleWebKit/537.36 (KHTML, like Gecko) Chrome/109.0.0.0 Safari/537.36"/>
    <responseHeaders>HTTP/1.1 200 OK&#xd;
Cache-Control: max-age=172800&#xd;
Content-Type: image/png&#xd;
Last-Modified: Thu, 19 Sep 2013 18:10:20 GMT&#xd;
Accept-Ranges: bytes&#xd;
ETag: "08e588063b5ce1:0"&#xd;
Server: Microsoft-IIS/10.0&#xd;
X-Powered-By: ASP.NET&#xd;
Date: Mon, 27 Feb 2023 19:24:41 GMT&#xd;
Content-Length: 1420</responseHeaders>
    <record-html-infos extractorRegExp="false" htmlType="0"/>
</http-action>
