<http-page executeResourcesDynamically="false" name="/qaphr998two/"
    playRequestsSequentially="false"
    recordedArtifactZipFileName="team/vus/@prism@h@r_@company_@details_@c4484560_@april/%resources%/recorded-artifacts/db02022a-1a46-48f4-bc30-a96130b7e861.zip"
    slaProfileEnabled="false" thinkTime="5000"
    thinkTimeMode="MODE_SIMPLE_THINK_TIME" thinkTimeRangeEnd=""
    thinkTimeRangeStart="" uid="db02022a-1a46-48f4-bc30-a96130b7e861">
    <embedded-action>2bc3ecfd-535f-45c6-9571-695ab8c411ea</embedded-action>
    <embedded-action>4e1cafdb-79ac-4cef-9d9a-02612c9adb9e</embedded-action>
    <embedded-action>38a5ad83-d419-4829-89bb-1bd2d54038c3</embedded-action>
    <embedded-action>3787fee8-cd5d-41ab-a300-991a7908e4b8</embedded-action>
    <embedded-action>51da150c-ec82-4c1e-bb49-f4f952f5be56</embedded-action>
    <embedded-action>5c3c38c9-486f-4a03-a08e-bd9b1a639b3f</embedded-action>
    <embedded-action>91fc7ea4-5344-4c32-b97c-d5ccf01223c1</embedded-action>
    <embedded-action>3af7dc0e-586f-4c5b-a0b7-d56b7f177b83</embedded-action>
    <embedded-action>4e7fd6d1-764b-4a22-bae0-8213a186f441</embedded-action>
    <embedded-action>a9d538bb-2ac7-4ab2-9745-34c411da4f33</embedded-action>
    <embedded-action>753773b8-6a40-4b2f-b3a1-746c241c17b8</embedded-action>
    <embedded-action>d9272fc1-65b2-438f-9be4-3909880a882e</embedded-action>
    <embedded-action>d14291df-47d2-4e97-80ad-8777efee359e</embedded-action>
    <embedded-action>2b473cde-dc06-461c-a75f-ed815ef54788</embedded-action>
    <embedded-action>abe57029-dd55-4ab6-a761-2b0a9394ebd5</embedded-action>
    <embedded-action>341aca85-71b7-428c-ba2a-687a3486e17d</embedded-action>
    <embedded-action>460937d8-0ed2-44b0-8e08-13ff56478e20</embedded-action>
</http-page>
<http-action actionType="1" contentType="text/html; charset=utf-8"
    extractorInjectPathPolicy="2" extractorPathPolicy="1"
    followRedirects="false" generatedByClient="false"
    linkExtractorSeveralMatchOccurrence="1"
    linkExtractorSeveralMatchPolicy="1" linkExtractorType="6"
    method="POST" name="/qaphr998two/" path="/qaphr998two/"
    postCharset="" postType="4"
    recordedArtifactZipFileName="team/vus/@prism@h@r_@company_@details_@c4484560_@april/%resources%/recorded-artifacts/db02022a-1a46-48f4-bc30-a96130b7e861.zip"
    recordedResponseCode="200" responseSize="58064"
    serverUid="qaphr998two.prismhr.com" slaProfileEnabled="false"
    uid="2bc3ecfd-535f-45c6-9571-695ab8c411ea" useKeepAlive="false">
    <responsePageFileDescription>recorded-responses/res_e99ed282-57b4-46b5-926b-42b40962dbd3.0.html</responsePageFileDescription>
    <requestContentFileDescription>recorded-requests/req_e99ed282-57b4-46b5-926b-42b40962dbd3.txt</requestContentFileDescription>
    <variable-extractor assertionOnNoMatch="true"
        defaultValue="&lt;NOT FOUND>" displayMode="1" endsWithSimple=""
        extractFromVarNameAdv="" extractFromVarNameSimple=""
        extractType="1" extractTypeAdv="1" extractTypeSimple="0"
        matchNumber="1" matchNumberAdv="1" matchNumberSimple="1"
        name="IDBrowser" regExp="IDBrowser=(.*?);"
        regExpAdv="IDBrowser=(.*?);" setDefaultValue="true"
        startsWithSimple="" template="$1$" templateAdv="$1$"
        uid="d64cebb6-5d3d-45e7-a0fa-7b65c2e12cc1" xpath=""/>
    <variable-extractor assertionOnNoMatch="true"
        defaultValue="&lt;NOT FOUND>" displayMode="0"
        endsWithSimple="');" extractFromVarNameAdv=""
        extractFromVarNameSimple="" extractType="0" extractTypeAdv="0"
        extractTypeSimple="0" matchNumber="1" matchNumberAdv="1"
        matchNumberSimple="1" name="Design_Bais"
        refererUid="6811a73c-ab17-404d-a5a5-d7b2a13ea24a"
        regExp="\('designbaisState', '(.*?)'\);" regExpAdv=""
        setDefaultValue="true" startsWithSimple="('designbaisState', '"
        template="$1$" templateAdv="$1$"
        uid="695d7718-3132-44ba-bb68-82b44f7c78c4" xpath="">
        <variable-extractor-group extract="true" occurs="1" pattern="" type="4"/>
    </variable-extractor>
    <header name="Accept" value="*/*"/>
    <header name="Accept-Encoding" value="gzip, deflate, br"/>
    <header name="Accept-Language" value="en-US,en;q=0.9"/>
    <header name="Connection" value="keep-alive"/>
    <header name="Content-Type" value="text/xml"/>
    <header name="Cookie" value="DesignBAIS=machine=KAWXLIBYIGQPWGBQKBSPWVMNSQVYWBPGTBKEZDQVGXNCXKR&amp;pooler=862&amp;ver=40; IDBrowser=${IDBrowser}"/>
    <header name="Host" value="qaphr998two.prismhr.com"/>
    <header name="Origin" value="https://qaphr998two.prismhr.com"/>
    <header name="Referer" value="https://qaphr998two.prismhr.com/qaphr998two/"/>
    <header name="sec-ch-ua" value="&quot;Not_A Brand&quot;;v=&quot;99&quot;, &quot;Google Chrome&quot;;v=&quot;109&quot;, &quot;Chromium&quot;;v=&quot;109&quot;"/>
    <header name="sec-ch-ua-mobile" value="?0"/>
    <header name="sec-ch-ua-platform" value="&quot;Windows&quot;"/>
    <header name="Sec-Fetch-Dest" value="empty"/>
    <header name="Sec-Fetch-Mode" value="cors"/>
    <header name="Sec-Fetch-Site" value="same-origin"/>
    <header name="User-Agent" value="Mozilla/5.0 (Windows NT 10.0; Win64; x64) AppleWebKit/537.36 (KHTML, like Gecko) Chrome/109.0.0.0 Safari/537.36"/>
    <header name="X-Requested-With" value="XMLHttpRequest"/>
    <responseHeaders>HTTP/1.1 200 OK&#xd;
Cache-Control: private&#xd;
Content-Type: text/html; charset=utf-8&#xd;
Server: Microsoft-IIS/10.0&#xd;
X-AspNet-Version: 4.0.30319&#xd;
Set-Cookie: IDBrowser=bba213b0696f4d18a52108cabebe53c83746f7d59fee195b8d055dfd77674cb2B8TTKLuD1qCTEfAJMgPflon84Gznj+4d+VbLjce6ThE=; expires=Wed, 19-Apr-2023 13:09:34 GMT; path=/; HttpOnly&#xd;
X-Powered-By: ASP.NET&#xd;
Date: Tue, 11 Apr 2023 13:09:35 GMT&#xd;
Content-Length: 58064</responseHeaders>
    <record-html-infos extractorRegExp="false" htmlType="0"/>
    <textPostContent><![CDATA[<AJAX><field  name="text4v1" value="peo87001"/><field  name="password6v1" value="Password99"/><field  name="dblastdb1formlayer" value=""/><field  name="ScreenRoot" value="HRPY.WORK_LOGIN"/><eventSource>button8v1</eventSource><eventType>click</eventType><clickPos>739,348,BUTTON,button8v1,671,348</clickPos><keyCodes>||||</keyCodes><dimensions>1536|710|1536|710</dimensions><designbaisState>${Design_Bais}</designbaisState><req>${regkey.dbsuiID}</req><tabStore>${Tstore}</tabStore><captchaKey>null</captchaKey><clientClock>08:09:34</clientClock><clientDate>11.04.2023</clientDate><mobile>false</mobile><lastMVCell></lastMVCell><scrollbarWidth>17</scrollbarWidth></AJAX>]]></textPostContent>
</http-action>
<http-action actionType="1" contentType="image/gif"
    eTag="&quot;09b69cde3e9cc1:0&quot;" extractorInjectPathPolicy="2"
    extractorPathPolicy="1" followRedirects="false"
    generatedByClient="false"
    lastModified="Mon, 13 Feb 2012 00:09:50 GMT"
    linkExtractorSeveralMatchOccurrence="1"
    linkExtractorSeveralMatchPolicy="1" linkExtractorType="6"
    method="GET" name="/qaphr998two/images/vision/tphidemenu.gif"
    path="/qaphr998two/images/vision/tphidemenu.gif" postType="6"
    recordedArtifactZipFileName="team/vus/@prism@h@r_@company_@details_@c4484560_@april/%resources%/recorded-artifacts/db02022a-1a46-48f4-bc30-a96130b7e861.zip"
    recordedResponseCode="200" responseSize="0"
    serverUid="qaphr998two.prismhr.com" slaProfileEnabled="false"
    uid="4e1cafdb-79ac-4cef-9d9a-02612c9adb9e" useKeepAlive="false">
    <requestContentFileDescription>recorded-requests/req_216ac81c-7cb1-4726-a46f-ee60d8aa35f1.txt</requestContentFileDescription>
    <header name="Accept" value="image/avif,image/webp,image/apng,image/svg+xml,image/*,*/*;q=0.8"/>
    <header name="Accept-Encoding" value="gzip, deflate, br"/>
    <header name="Accept-Language" value="en-US,en;q=0.9"/>
    <header name="Connection" value="keep-alive"/>
    <header name="Cookie" value="DesignBAIS=machine=KAWXLIBYIGQPWGBQKBSPWVMNSQVYWBPGTBKEZDQVGXNCXKR&amp;pooler=862&amp;ver=40; IDBrowser=${IDBrowser}"/>
    <header name="Host" value="qaphr998two.prismhr.com"/>
    <header name="Referer" value="https://qaphr998two.prismhr.com/qaphr998two/"/>
    <header name="sec-ch-ua" value="&quot;Not_A Brand&quot;;v=&quot;99&quot;, &quot;Google Chrome&quot;;v=&quot;109&quot;, &quot;Chromium&quot;;v=&quot;109&quot;"/>
    <header name="sec-ch-ua-mobile" value="?0"/>
    <header name="sec-ch-ua-platform" value="&quot;Windows&quot;"/>
    <header name="Sec-Fetch-Dest" value="image"/>
    <header name="Sec-Fetch-Mode" value="no-cors"/>
    <header name="Sec-Fetch-Site" value="same-origin"/>
    <header name="User-Agent" value="Mozilla/5.0 (Windows NT 10.0; Win64; x64) AppleWebKit/537.36 (KHTML, like Gecko) Chrome/109.0.0.0 Safari/537.36"/>
    <responseHeaders>HTTP/1.1 200 OK&#xd;
Cache-Control: max-age=172800&#xd;
Content-Type: image/gif&#xd;
Last-Modified: Mon, 13 Feb 2012 00:09:50 GMT&#xd;
Accept-Ranges: bytes&#xd;
ETag: "09b69cde3e9cc1:0"&#xd;
Server: Microsoft-IIS/10.0&#xd;
X-Powered-By: ASP.NET&#xd;
Date: Tue, 11 Apr 2023 13:09:35 GMT&#xd;
Content-Length: 79</responseHeaders>
    <record-html-infos extractorRegExp="false" htmlType="0"/>
</http-action>
<http-action actionType="1" contentType="image/gif"
    eTag="&quot;09b69cde3e9cc1:0&quot;" extractorInjectPathPolicy="2"
    extractorPathPolicy="1" followRedirects="false"
    generatedByClient="false"
    lastModified="Mon, 13 Feb 2012 00:09:50 GMT"
    linkExtractorSeveralMatchOccurrence="1"
    linkExtractorSeveralMatchPolicy="1" linkExtractorType="6"
    method="GET" name="/qaphr998two/images/vision/tphideuserinfo.gif"
    path="/qaphr998two/images/vision/tphideuserinfo.gif" postType="6"
    recordedArtifactZipFileName="team/vus/@prism@h@r_@company_@details_@c4484560_@april/%resources%/recorded-artifacts/db02022a-1a46-48f4-bc30-a96130b7e861.zip"
    recordedResponseCode="200" responseSize="0"
    serverUid="qaphr998two.prismhr.com" slaProfileEnabled="false"
    uid="38a5ad83-d419-4829-89bb-1bd2d54038c3" useKeepAlive="false">
    <requestContentFileDescription>recorded-requests/req_eedc2150-61c4-440c-84d8-4b631a2eeb36.txt</requestContentFileDescription>
    <header name="Accept" value="image/avif,image/webp,image/apng,image/svg+xml,image/*,*/*;q=0.8"/>
    <header name="Accept-Encoding" value="gzip, deflate, br"/>
    <header name="Accept-Language" value="en-US,en;q=0.9"/>
    <header name="Connection" value="keep-alive"/>
    <header name="Cookie" value="DesignBAIS=machine=KAWXLIBYIGQPWGBQKBSPWVMNSQVYWBPGTBKEZDQVGXNCXKR&amp;pooler=862&amp;ver=40; IDBrowser=${IDBrowser}"/>
    <header name="Host" value="qaphr998two.prismhr.com"/>
    <header name="Referer" value="https://qaphr998two.prismhr.com/qaphr998two/"/>
    <header name="sec-ch-ua" value="&quot;Not_A Brand&quot;;v=&quot;99&quot;, &quot;Google Chrome&quot;;v=&quot;109&quot;, &quot;Chromium&quot;;v=&quot;109&quot;"/>
    <header name="sec-ch-ua-mobile" value="?0"/>
    <header name="sec-ch-ua-platform" value="&quot;Windows&quot;"/>
    <header name="Sec-Fetch-Dest" value="image"/>
    <header name="Sec-Fetch-Mode" value="no-cors"/>
    <header name="Sec-Fetch-Site" value="same-origin"/>
    <header name="User-Agent" value="Mozilla/5.0 (Windows NT 10.0; Win64; x64) AppleWebKit/537.36 (KHTML, like Gecko) Chrome/109.0.0.0 Safari/537.36"/>
    <responseHeaders>HTTP/1.1 200 OK&#xd;
Cache-Control: max-age=172800&#xd;
Content-Type: image/gif&#xd;
Last-Modified: Mon, 13 Feb 2012 00:09:50 GMT&#xd;
Accept-Ranges: bytes&#xd;
ETag: "09b69cde3e9cc1:0"&#xd;
Server: Microsoft-IIS/10.0&#xd;
X-Powered-By: ASP.NET&#xd;
Date: Tue, 11 Apr 2023 13:09:35 GMT&#xd;
Content-Length: 79</responseHeaders>
    <record-html-infos extractorRegExp="false" htmlType="0"/>
</http-action>
<http-action actionType="1" contentType="image/png"
    eTag="&quot;0ef3c22fd28d01:0&quot;" extractorInjectPathPolicy="2"
    extractorPathPolicy="1" followRedirects="false"
    generatedByClient="false"
    lastModified="Mon, 05 Jan 2015 15:34:46 GMT"
    linkExtractorSeveralMatchOccurrence="1"
    linkExtractorSeveralMatchPolicy="1" linkExtractorType="6"
    method="GET" name="/qaphr998two/images/vision/icon_search.png"
    path="/qaphr998two/images/vision/icon_search.png" postType="6"
    recordedArtifactZipFileName="team/vus/@prism@h@r_@company_@details_@c4484560_@april/%resources%/recorded-artifacts/db02022a-1a46-48f4-bc30-a96130b7e861.zip"
    recordedResponseCode="200" responseSize="0"
    serverUid="qaphr998two.prismhr.com" slaProfileEnabled="false"
    uid="3787fee8-cd5d-41ab-a300-991a7908e4b8" useKeepAlive="false">
    <requestContentFileDescription>recorded-requests/req_8101496d-b409-4e2a-a265-ca30bcf89e67.txt</requestContentFileDescription>
    <header name="Accept" value="image/avif,image/webp,image/apng,image/svg+xml,image/*,*/*;q=0.8"/>
    <header name="Accept-Encoding" value="gzip, deflate, br"/>
    <header name="Accept-Language" value="en-US,en;q=0.9"/>
    <header name="Connection" value="keep-alive"/>
    <header name="Cookie" value="DesignBAIS=machine=KAWXLIBYIGQPWGBQKBSPWVMNSQVYWBPGTBKEZDQVGXNCXKR&amp;pooler=862&amp;ver=40; IDBrowser=${IDBrowser}"/>
    <header name="Host" value="qaphr998two.prismhr.com"/>
    <header name="Referer" value="https://qaphr998two.prismhr.com/qaphr998two/"/>
    <header name="sec-ch-ua" value="&quot;Not_A Brand&quot;;v=&quot;99&quot;, &quot;Google Chrome&quot;;v=&quot;109&quot;, &quot;Chromium&quot;;v=&quot;109&quot;"/>
    <header name="sec-ch-ua-mobile" value="?0"/>
    <header name="sec-ch-ua-platform" value="&quot;Windows&quot;"/>
    <header name="Sec-Fetch-Dest" value="image"/>
    <header name="Sec-Fetch-Mode" value="no-cors"/>
    <header name="Sec-Fetch-Site" value="same-origin"/>
    <header name="User-Agent" value="Mozilla/5.0 (Windows NT 10.0; Win64; x64) AppleWebKit/537.36 (KHTML, like Gecko) Chrome/109.0.0.0 Safari/537.36"/>
    <responseHeaders>HTTP/1.1 200 OK&#xd;
Cache-Control: max-age=172800&#xd;
Content-Type: image/png&#xd;
Last-Modified: Mon, 05 Jan 2015 15:34:46 GMT&#xd;
Accept-Ranges: bytes&#xd;
ETag: "0ef3c22fd28d01:0"&#xd;
Server: Microsoft-IIS/10.0&#xd;
X-Powered-By: ASP.NET&#xd;
Date: Tue, 11 Apr 2023 13:09:35 GMT&#xd;
Content-Length: 5766</responseHeaders>
    <record-html-infos extractorRegExp="false" htmlType="0"/>
</http-action>
<http-action actionType="1" contentType="image/png"
    eTag="&quot;0eb4b65e1e9cd1:0&quot;" extractorInjectPathPolicy="2"
    extractorPathPolicy="1" followRedirects="false"
    generatedByClient="false"
    lastModified="Thu, 03 Jan 2013 18:37:34 GMT"
    linkExtractorSeveralMatchOccurrence="1"
    linkExtractorSeveralMatchPolicy="1" linkExtractorType="6"
    method="GET" name="/qaphr998two/images/vision/x.png"
    path="/qaphr998two/images/vision/x.png" postType="6"
    recordedArtifactZipFileName="team/vus/@prism@h@r_@company_@details_@c4484560_@april/%resources%/recorded-artifacts/db02022a-1a46-48f4-bc30-a96130b7e861.zip"
    recordedResponseCode="200" responseSize="0"
    serverUid="qaphr998two.prismhr.com" slaProfileEnabled="false"
    uid="51da150c-ec82-4c1e-bb49-f4f952f5be56" useKeepAlive="false">
    <requestContentFileDescription>recorded-requests/req_03f981fa-c833-470f-9af2-ca4038900314.txt</requestContentFileDescription>
    <header name="Accept" value="image/avif,image/webp,image/apng,image/svg+xml,image/*,*/*;q=0.8"/>
    <header name="Accept-Encoding" value="gzip, deflate, br"/>
    <header name="Accept-Language" value="en-US,en;q=0.9"/>
    <header name="Connection" value="keep-alive"/>
    <header name="Cookie" value="DesignBAIS=machine=KAWXLIBYIGQPWGBQKBSPWVMNSQVYWBPGTBKEZDQVGXNCXKR&amp;pooler=862&amp;ver=40; IDBrowser=${IDBrowser}"/>
    <header name="Host" value="qaphr998two.prismhr.com"/>
    <header name="Referer" value="https://qaphr998two.prismhr.com/qaphr998two/"/>
    <header name="sec-ch-ua" value="&quot;Not_A Brand&quot;;v=&quot;99&quot;, &quot;Google Chrome&quot;;v=&quot;109&quot;, &quot;Chromium&quot;;v=&quot;109&quot;"/>
    <header name="sec-ch-ua-mobile" value="?0"/>
    <header name="sec-ch-ua-platform" value="&quot;Windows&quot;"/>
    <header name="Sec-Fetch-Dest" value="image"/>
    <header name="Sec-Fetch-Mode" value="no-cors"/>
    <header name="Sec-Fetch-Site" value="same-origin"/>
    <header name="User-Agent" value="Mozilla/5.0 (Windows NT 10.0; Win64; x64) AppleWebKit/537.36 (KHTML, like Gecko) Chrome/109.0.0.0 Safari/537.36"/>
    <responseHeaders>HTTP/1.1 200 OK&#xd;
Cache-Control: max-age=172800&#xd;
Content-Type: image/png&#xd;
Last-Modified: Thu, 03 Jan 2013 18:37:34 GMT&#xd;
Accept-Ranges: bytes&#xd;
ETag: "0eb4b65e1e9cd1:0"&#xd;
Server: Microsoft-IIS/10.0&#xd;
X-Powered-By: ASP.NET&#xd;
Date: Tue, 11 Apr 2023 13:09:35 GMT&#xd;
Content-Length: 3444</responseHeaders>
    <record-html-infos extractorRegExp="false" htmlType="0"/>
</http-action>
<http-action actionType="1" contentType="image/gif"
    eTag="&quot;09b69cde3e9cc1:0&quot;" extractorInjectPathPolicy="2"
    extractorPathPolicy="1" followRedirects="false"
    generatedByClient="false"
    lastModified="Mon, 13 Feb 2012 00:09:50 GMT"
    linkExtractorSeveralMatchOccurrence="1"
    linkExtractorSeveralMatchPolicy="1" linkExtractorType="6"
    method="GET" name="/qaphr998two/images/vision/tphideactions.gif"
    path="/qaphr998two/images/vision/tphideactions.gif" postType="6"
    recordedArtifactZipFileName="team/vus/@prism@h@r_@company_@details_@c4484560_@april/%resources%/recorded-artifacts/db02022a-1a46-48f4-bc30-a96130b7e861.zip"
    recordedResponseCode="200" responseSize="0"
    serverUid="qaphr998two.prismhr.com" slaProfileEnabled="false"
    uid="5c3c38c9-486f-4a03-a08e-bd9b1a639b3f" useKeepAlive="false">
    <requestContentFileDescription>recorded-requests/req_f3fba53b-2cd3-413c-8d2f-0515ac142af7.txt</requestContentFileDescription>
    <header name="Accept" value="image/avif,image/webp,image/apng,image/svg+xml,image/*,*/*;q=0.8"/>
    <header name="Accept-Encoding" value="gzip, deflate, br"/>
    <header name="Accept-Language" value="en-US,en;q=0.9"/>
    <header name="Connection" value="keep-alive"/>
    <header name="Cookie" value="DesignBAIS=machine=KAWXLIBYIGQPWGBQKBSPWVMNSQVYWBPGTBKEZDQVGXNCXKR&amp;pooler=862&amp;ver=40; IDBrowser=${IDBrowser}"/>
    <header name="Host" value="qaphr998two.prismhr.com"/>
    <header name="Referer" value="https://qaphr998two.prismhr.com/qaphr998two/"/>
    <header name="sec-ch-ua" value="&quot;Not_A Brand&quot;;v=&quot;99&quot;, &quot;Google Chrome&quot;;v=&quot;109&quot;, &quot;Chromium&quot;;v=&quot;109&quot;"/>
    <header name="sec-ch-ua-mobile" value="?0"/>
    <header name="sec-ch-ua-platform" value="&quot;Windows&quot;"/>
    <header name="Sec-Fetch-Dest" value="image"/>
    <header name="Sec-Fetch-Mode" value="no-cors"/>
    <header name="Sec-Fetch-Site" value="same-origin"/>
    <header name="User-Agent" value="Mozilla/5.0 (Windows NT 10.0; Win64; x64) AppleWebKit/537.36 (KHTML, like Gecko) Chrome/109.0.0.0 Safari/537.36"/>
    <responseHeaders>HTTP/1.1 200 OK&#xd;
Cache-Control: max-age=172800&#xd;
Content-Type: image/gif&#xd;
Last-Modified: Mon, 13 Feb 2012 00:09:50 GMT&#xd;
Accept-Ranges: bytes&#xd;
ETag: "09b69cde3e9cc1:0"&#xd;
Server: Microsoft-IIS/10.0&#xd;
X-Powered-By: ASP.NET&#xd;
Date: Tue, 11 Apr 2023 13:09:35 GMT&#xd;
Content-Length: 79</responseHeaders>
    <record-html-infos extractorRegExp="false" htmlType="0"/>
</http-action>
<http-action actionType="1" contentType="font/woff2"
    eTag="&quot;610ae361-17e0&quot;" extractorInjectPathPolicy="2"
    extractorPathPolicy="1" followRedirects="false"
    generatedByClient="false"
    lastModified="Wed, 04 Aug 2021 18:58:41 GMT"
    linkExtractorSeveralMatchOccurrence="1"
    linkExtractorSeveralMatchPolicy="1" linkExtractorType="6"
    method="GET"
    name="/releases/v5.15.4/webfonts/pro-fa-solid-900-5.0.9.woff2"
    path="/releases/v5.15.4/webfonts/pro-fa-solid-900-5.0.9.woff2"
    postType="6"
    recordedArtifactZipFileName="team/vus/@prism@h@r_@company_@details_@c4484560_@april/%resources%/recorded-artifacts/db02022a-1a46-48f4-bc30-a96130b7e861.zip"
    recordedResponseCode="200" responseSize="0"
    serverUid="imported_ka-p.fontawesome.com" slaProfileEnabled="false"
    uid="91fc7ea4-5344-4c32-b97c-d5ccf01223c1" useKeepAlive="false">
    <requestContentFileDescription>recorded-requests/req_fb9e5248-90b8-47cd-b99c-c7b349618c39.txt</requestContentFileDescription>
    <header name="sec-fetch-mode" value="cors"/>
    <header name="referer" value="https://qaphr998two.prismhr.com/"/>
    <header name="sec-ch-ua" value="&quot;Not_A Brand&quot;;v=&quot;99&quot;, &quot;Google Chrome&quot;;v=&quot;109&quot;, &quot;Chromium&quot;;v=&quot;109&quot;"/>
    <header name="sec-fetch-site" value="cross-site"/>
    <header name="sec-ch-ua-mobile" value="?0"/>
    <header name="accept-language" value="en-US,en;q=0.9"/>
    <header name="sec-ch-ua-platform" value="&quot;Windows&quot;"/>
    <header name="origin" value="https://qaphr998two.prismhr.com"/>
    <header name="accept-encoding" value="gzip, deflate, br"/>
    <header name="sec-fetch-dest" value="font"/>
    <header name="accept" value="*/*"/>
    <header name="user-agent" value="Mozilla/5.0 (Windows NT 10.0; Win64; x64) AppleWebKit/537.36 (KHTML, like Gecko) Chrome/109.0.0.0 Safari/537.36"/>
    <responseHeaders>HTTP/2.0 200&#xd;
date: Tue, 11 Apr 2023 13:09:35 GMT&#xd;
content-type: font/woff2&#xd;
content-length: 6112&#xd;
access-control-allow-origin: *&#xd;
cache-control: max-age=31556926&#xd;
etag: "610ae361-17e0"&#xd;
last-modified: Wed, 04 Aug 2021 18:58:41 GMT&#xd;
vary: Origin, Accept-Encoding, Access-Control-Request-Headers, Access-Control-Request-Method&#xd;
cf-cache-status: MISS&#xd;
accept-ranges: bytes&#xd;
server: cloudflare&#xd;
cf-ray: 7b6376fea9fde976-DFW</responseHeaders>
    <record-html-infos extractorRegExp="false" htmlType="0"/>
</http-action>
<http-action actionType="1" contentType="font/woff2"
    eTag="&quot;610ae361-33d4&quot;" extractorInjectPathPolicy="2"
    extractorPathPolicy="1" followRedirects="false"
    generatedByClient="false"
    lastModified="Wed, 04 Aug 2021 18:58:41 GMT"
    linkExtractorSeveralMatchOccurrence="1"
    linkExtractorSeveralMatchPolicy="1" linkExtractorType="6"
    method="GET"
    name="/releases/v5.15.4/webfonts/pro-fa-solid-900-5.10.2.woff2"
    path="/releases/v5.15.4/webfonts/pro-fa-solid-900-5.10.2.woff2"
    postType="6"
    recordedArtifactZipFileName="team/vus/@prism@h@r_@company_@details_@c4484560_@april/%resources%/recorded-artifacts/db02022a-1a46-48f4-bc30-a96130b7e861.zip"
    recordedResponseCode="200" responseSize="0"
    serverUid="imported_ka-p.fontawesome.com" slaProfileEnabled="false"
    uid="3af7dc0e-586f-4c5b-a0b7-d56b7f177b83" useKeepAlive="false">
    <requestContentFileDescription>recorded-requests/req_492de6bb-2375-427c-9100-69a1dce66cf7.txt</requestContentFileDescription>
    <header name="sec-fetch-mode" value="cors"/>
    <header name="referer" value="https://qaphr998two.prismhr.com/"/>
    <header name="sec-ch-ua" value="&quot;Not_A Brand&quot;;v=&quot;99&quot;, &quot;Google Chrome&quot;;v=&quot;109&quot;, &quot;Chromium&quot;;v=&quot;109&quot;"/>
    <header name="sec-fetch-site" value="cross-site"/>
    <header name="sec-ch-ua-mobile" value="?0"/>
    <header name="accept-language" value="en-US,en;q=0.9"/>
    <header name="sec-ch-ua-platform" value="&quot;Windows&quot;"/>
    <header name="origin" value="https://qaphr998two.prismhr.com"/>
    <header name="accept-encoding" value="gzip, deflate, br"/>
    <header name="sec-fetch-dest" value="font"/>
    <header name="accept" value="*/*"/>
    <header name="user-agent" value="Mozilla/5.0 (Windows NT 10.0; Win64; x64) AppleWebKit/537.36 (KHTML, like Gecko) Chrome/109.0.0.0 Safari/537.36"/>
    <responseHeaders>HTTP/2.0 200&#xd;
date: Tue, 11 Apr 2023 13:09:35 GMT&#xd;
content-type: font/woff2&#xd;
content-length: 13268&#xd;
access-control-allow-origin: *&#xd;
cache-control: max-age=31556926&#xd;
etag: "610ae361-33d4"&#xd;
last-modified: Wed, 04 Aug 2021 18:58:41 GMT&#xd;
vary: Origin, Accept-Encoding, Access-Control-Request-Headers, Access-Control-Request-Method&#xd;
cf-cache-status: MISS&#xd;
accept-ranges: bytes&#xd;
server: cloudflare&#xd;
cf-ray: 7b6376fefa58e976-DFW</responseHeaders>
    <record-html-infos extractorRegExp="false" htmlType="0"/>
</http-action>
<http-action actionType="1" contentType="font/woff2"
    eTag="&quot;610ae35d-2550&quot;" extractorInjectPathPolicy="2"
    extractorPathPolicy="1" followRedirects="false"
    generatedByClient="false"
    lastModified="Wed, 04 Aug 2021 18:58:37 GMT"
    linkExtractorSeveralMatchOccurrence="1"
    linkExtractorSeveralMatchPolicy="1" linkExtractorType="6"
    method="GET"
    name="/releases/v5.15.4/webfonts/pro-fa-regular-400-5.11.1.woff2"
    path="/releases/v5.15.4/webfonts/pro-fa-regular-400-5.11.1.woff2"
    postType="6"
    recordedArtifactZipFileName="team/vus/@prism@h@r_@company_@details_@c4484560_@april/%resources%/recorded-artifacts/db02022a-1a46-48f4-bc30-a96130b7e861.zip"
    recordedResponseCode="200" responseSize="0"
    serverUid="imported_ka-p.fontawesome.com" slaProfileEnabled="false"
    uid="4e7fd6d1-764b-4a22-bae0-8213a186f441" useKeepAlive="false">
    <requestContentFileDescription>recorded-requests/req_1ec669ea-6313-4de2-a460-426c9f4631b3.txt</requestContentFileDescription>
    <header name="sec-fetch-mode" value="cors"/>
    <header name="referer" value="https://qaphr998two.prismhr.com/"/>
    <header name="sec-ch-ua" value="&quot;Not_A Brand&quot;;v=&quot;99&quot;, &quot;Google Chrome&quot;;v=&quot;109&quot;, &quot;Chromium&quot;;v=&quot;109&quot;"/>
    <header name="sec-fetch-site" value="cross-site"/>
    <header name="sec-ch-ua-mobile" value="?0"/>
    <header name="accept-language" value="en-US,en;q=0.9"/>
    <header name="sec-ch-ua-platform" value="&quot;Windows&quot;"/>
    <header name="origin" value="https://qaphr998two.prismhr.com"/>
    <header name="accept-encoding" value="gzip, deflate, br"/>
    <header name="sec-fetch-dest" value="font"/>
    <header name="accept" value="*/*"/>
    <header name="user-agent" value="Mozilla/5.0 (Windows NT 10.0; Win64; x64) AppleWebKit/537.36 (KHTML, like Gecko) Chrome/109.0.0.0 Safari/537.36"/>
    <responseHeaders>HTTP/2.0 200&#xd;
date: Tue, 11 Apr 2023 13:09:35 GMT&#xd;
content-type: font/woff2&#xd;
content-length: 9552&#xd;
access-control-allow-origin: *&#xd;
cache-control: max-age=31556926&#xd;
etag: "610ae35d-2550"&#xd;
last-modified: Wed, 04 Aug 2021 18:58:37 GMT&#xd;
vary: Origin, Accept-Encoding, Access-Control-Request-Headers, Access-Control-Request-Method&#xd;
cf-cache-status: MISS&#xd;
accept-ranges: bytes&#xd;
server: cloudflare&#xd;
cf-ray: 7b6376fefa59e976-DFW</responseHeaders>
    <record-html-infos extractorRegExp="false" htmlType="0"/>
</http-action>
<http-action actionType="1" contentType="font/woff2"
    eTag="&quot;610ae362-2144&quot;" extractorInjectPathPolicy="2"
    extractorPathPolicy="1" followRedirects="false"
    generatedByClient="false"
    lastModified="Wed, 04 Aug 2021 18:58:42 GMT"
    linkExtractorSeveralMatchOccurrence="1"
    linkExtractorSeveralMatchPolicy="1" linkExtractorType="6"
    method="GET"
    name="/releases/v5.15.4/webfonts/pro-fa-solid-900-5.11.1.woff2"
    path="/releases/v5.15.4/webfonts/pro-fa-solid-900-5.11.1.woff2"
    postType="6"
    recordedArtifactZipFileName="team/vus/@prism@h@r_@company_@details_@c4484560_@april/%resources%/recorded-artifacts/db02022a-1a46-48f4-bc30-a96130b7e861.zip"
    recordedResponseCode="200" responseSize="0"
    serverUid="imported_ka-p.fontawesome.com" slaProfileEnabled="false"
    uid="a9d538bb-2ac7-4ab2-9745-34c411da4f33" useKeepAlive="false">
    <requestContentFileDescription>recorded-requests/req_1c8d322b-fc2b-45e9-90b9-bcf25ca97045.txt</requestContentFileDescription>
    <header name="sec-fetch-mode" value="cors"/>
    <header name="referer" value="https://qaphr998two.prismhr.com/"/>
    <header name="sec-ch-ua" value="&quot;Not_A Brand&quot;;v=&quot;99&quot;, &quot;Google Chrome&quot;;v=&quot;109&quot;, &quot;Chromium&quot;;v=&quot;109&quot;"/>
    <header name="sec-fetch-site" value="cross-site"/>
    <header name="sec-ch-ua-mobile" value="?0"/>
    <header name="accept-language" value="en-US,en;q=0.9"/>
    <header name="sec-ch-ua-platform" value="&quot;Windows&quot;"/>
    <header name="origin" value="https://qaphr998two.prismhr.com"/>
    <header name="accept-encoding" value="gzip, deflate, br"/>
    <header name="sec-fetch-dest" value="font"/>
    <header name="accept" value="*/*"/>
    <header name="user-agent" value="Mozilla/5.0 (Windows NT 10.0; Win64; x64) AppleWebKit/537.36 (KHTML, like Gecko) Chrome/109.0.0.0 Safari/537.36"/>
    <responseHeaders>HTTP/2.0 200&#xd;
date: Tue, 11 Apr 2023 13:09:35 GMT&#xd;
content-type: font/woff2&#xd;
content-length: 8516&#xd;
access-control-allow-origin: *&#xd;
cache-control: max-age=31556926&#xd;
etag: "610ae362-2144"&#xd;
last-modified: Wed, 04 Aug 2021 18:58:42 GMT&#xd;
vary: Origin, Accept-Encoding, Access-Control-Request-Headers, Access-Control-Request-Method&#xd;
cf-cache-status: MISS&#xd;
accept-ranges: bytes&#xd;
server: cloudflare&#xd;
cf-ray: 7b6376fefa5ae976-DFW</responseHeaders>
    <record-html-infos extractorRegExp="false" htmlType="0"/>
</http-action>
<http-action actionType="1" contentType="font/woff2"
    eTag="&quot;610ae360-c6c&quot;" extractorInjectPathPolicy="2"
    extractorPathPolicy="1" followRedirects="false"
    generatedByClient="false"
    lastModified="Wed, 04 Aug 2021 18:58:40 GMT"
    linkExtractorSeveralMatchOccurrence="1"
    linkExtractorSeveralMatchPolicy="1" linkExtractorType="6"
    method="GET"
    name="/releases/v5.15.4/webfonts/pro-fa-solid-900-5.0.11.woff2"
    path="/releases/v5.15.4/webfonts/pro-fa-solid-900-5.0.11.woff2"
    postType="6"
    recordedArtifactZipFileName="team/vus/@prism@h@r_@company_@details_@c4484560_@april/%resources%/recorded-artifacts/db02022a-1a46-48f4-bc30-a96130b7e861.zip"
    recordedResponseCode="200" responseSize="0"
    serverUid="imported_ka-p.fontawesome.com" slaProfileEnabled="false"
    uid="753773b8-6a40-4b2f-b3a1-746c241c17b8" useKeepAlive="false">
    <requestContentFileDescription>recorded-requests/req_68043aa5-2f85-4d31-a7e3-8619d73c2d1c.txt</requestContentFileDescription>
    <header name="sec-fetch-mode" value="cors"/>
    <header name="referer" value="https://qaphr998two.prismhr.com/"/>
    <header name="sec-ch-ua" value="&quot;Not_A Brand&quot;;v=&quot;99&quot;, &quot;Google Chrome&quot;;v=&quot;109&quot;, &quot;Chromium&quot;;v=&quot;109&quot;"/>
    <header name="sec-fetch-site" value="cross-site"/>
    <header name="sec-ch-ua-mobile" value="?0"/>
    <header name="accept-language" value="en-US,en;q=0.9"/>
    <header name="sec-ch-ua-platform" value="&quot;Windows&quot;"/>
    <header name="origin" value="https://qaphr998two.prismhr.com"/>
    <header name="accept-encoding" value="gzip, deflate, br"/>
    <header name="sec-fetch-dest" value="font"/>
    <header name="accept" value="*/*"/>
    <header name="user-agent" value="Mozilla/5.0 (Windows NT 10.0; Win64; x64) AppleWebKit/537.36 (KHTML, like Gecko) Chrome/109.0.0.0 Safari/537.36"/>
    <responseHeaders>HTTP/2.0 200&#xd;
date: Tue, 11 Apr 2023 13:09:35 GMT&#xd;
content-type: font/woff2&#xd;
content-length: 3180&#xd;
access-control-allow-origin: *&#xd;
cache-control: max-age=31556926&#xd;
etag: "610ae360-c6c"&#xd;
last-modified: Wed, 04 Aug 2021 18:58:40 GMT&#xd;
vary: Origin, Accept-Encoding, Access-Control-Request-Headers, Access-Control-Request-Method&#xd;
cf-cache-status: MISS&#xd;
accept-ranges: bytes&#xd;
server: cloudflare&#xd;
cf-ray: 7b6376fefa5ce976-DFW</responseHeaders>
    <record-html-infos extractorRegExp="false" htmlType="0"/>
</http-action>
<http-action actionType="1" contentType="font/woff2"
    eTag="&quot;610ae362-2314&quot;" extractorInjectPathPolicy="2"
    extractorPathPolicy="1" followRedirects="false"
    generatedByClient="false"
    lastModified="Wed, 04 Aug 2021 18:58:42 GMT"
    linkExtractorSeveralMatchOccurrence="1"
    linkExtractorSeveralMatchPolicy="1" linkExtractorType="6"
    method="GET"
    name="/releases/v5.15.4/webfonts/pro-fa-solid-900-5.3.0.woff2"
    path="/releases/v5.15.4/webfonts/pro-fa-solid-900-5.3.0.woff2"
    postType="6"
    recordedArtifactZipFileName="team/vus/@prism@h@r_@company_@details_@c4484560_@april/%resources%/recorded-artifacts/db02022a-1a46-48f4-bc30-a96130b7e861.zip"
    recordedResponseCode="200" responseSize="0"
    serverUid="imported_ka-p.fontawesome.com" slaProfileEnabled="false"
    uid="d9272fc1-65b2-438f-9be4-3909880a882e" useKeepAlive="false">
    <requestContentFileDescription>recorded-requests/req_b05b0295-267c-4beb-bbe6-bbe7f6954ba1.txt</requestContentFileDescription>
    <header name="sec-fetch-mode" value="cors"/>
    <header name="referer" value="https://qaphr998two.prismhr.com/"/>
    <header name="sec-ch-ua" value="&quot;Not_A Brand&quot;;v=&quot;99&quot;, &quot;Google Chrome&quot;;v=&quot;109&quot;, &quot;Chromium&quot;;v=&quot;109&quot;"/>
    <header name="sec-fetch-site" value="cross-site"/>
    <header name="sec-ch-ua-mobile" value="?0"/>
    <header name="accept-language" value="en-US,en;q=0.9"/>
    <header name="sec-ch-ua-platform" value="&quot;Windows&quot;"/>
    <header name="origin" value="https://qaphr998two.prismhr.com"/>
    <header name="accept-encoding" value="gzip, deflate, br"/>
    <header name="sec-fetch-dest" value="font"/>
    <header name="accept" value="*/*"/>
    <header name="user-agent" value="Mozilla/5.0 (Windows NT 10.0; Win64; x64) AppleWebKit/537.36 (KHTML, like Gecko) Chrome/109.0.0.0 Safari/537.36"/>
    <responseHeaders>HTTP/2.0 200&#xd;
date: Tue, 11 Apr 2023 13:09:35 GMT&#xd;
content-type: font/woff2&#xd;
content-length: 8980&#xd;
access-control-allow-origin: *&#xd;
cache-control: max-age=31556926&#xd;
etag: "610ae362-2314"&#xd;
last-modified: Wed, 04 Aug 2021 18:58:42 GMT&#xd;
vary: Origin, Accept-Encoding, Access-Control-Request-Headers, Access-Control-Request-Method&#xd;
cf-cache-status: MISS&#xd;
accept-ranges: bytes&#xd;
server: cloudflare&#xd;
cf-ray: 7b6376fefa5ee976-DFW</responseHeaders>
    <record-html-infos extractorRegExp="false" htmlType="0"/>
</http-action>
<http-action actionType="1" contentType="font/woff2"
    eTag="&quot;610ae363-1bc8&quot;" extractorInjectPathPolicy="2"
    extractorPathPolicy="1" followRedirects="false"
    generatedByClient="false"
    lastModified="Wed, 04 Aug 2021 18:58:43 GMT"
    linkExtractorSeveralMatchOccurrence="1"
    linkExtractorSeveralMatchPolicy="1" linkExtractorType="6"
    method="GET"
    name="/releases/v5.15.4/webfonts/pro-fa-solid-900-5.5.0.woff2"
    path="/releases/v5.15.4/webfonts/pro-fa-solid-900-5.5.0.woff2"
    postType="6"
    recordedArtifactZipFileName="team/vus/@prism@h@r_@company_@details_@c4484560_@april/%resources%/recorded-artifacts/db02022a-1a46-48f4-bc30-a96130b7e861.zip"
    recordedResponseCode="200" responseSize="0"
    serverUid="imported_ka-p.fontawesome.com" slaProfileEnabled="false"
    uid="d14291df-47d2-4e97-80ad-8777efee359e" useKeepAlive="false">
    <requestContentFileDescription>recorded-requests/req_b7282e98-3c30-4500-82a8-d2b969d0c4e9.txt</requestContentFileDescription>
    <header name="sec-fetch-mode" value="cors"/>
    <header name="referer" value="https://qaphr998two.prismhr.com/"/>
    <header name="sec-ch-ua" value="&quot;Not_A Brand&quot;;v=&quot;99&quot;, &quot;Google Chrome&quot;;v=&quot;109&quot;, &quot;Chromium&quot;;v=&quot;109&quot;"/>
    <header name="sec-fetch-site" value="cross-site"/>
    <header name="sec-ch-ua-mobile" value="?0"/>
    <header name="accept-language" value="en-US,en;q=0.9"/>
    <header name="sec-ch-ua-platform" value="&quot;Windows&quot;"/>
    <header name="origin" value="https://qaphr998two.prismhr.com"/>
    <header name="accept-encoding" value="gzip, deflate, br"/>
    <header name="sec-fetch-dest" value="font"/>
    <header name="accept" value="*/*"/>
    <header name="user-agent" value="Mozilla/5.0 (Windows NT 10.0; Win64; x64) AppleWebKit/537.36 (KHTML, like Gecko) Chrome/109.0.0.0 Safari/537.36"/>
    <responseHeaders>HTTP/2.0 200&#xd;
date: Tue, 11 Apr 2023 13:09:35 GMT&#xd;
content-type: font/woff2&#xd;
content-length: 7112&#xd;
access-control-allow-origin: *&#xd;
cache-control: max-age=31556926&#xd;
etag: "610ae363-1bc8"&#xd;
last-modified: Wed, 04 Aug 2021 18:58:43 GMT&#xd;
vary: Origin, Accept-Encoding, Access-Control-Request-Headers, Access-Control-Request-Method&#xd;
cf-cache-status: MISS&#xd;
accept-ranges: bytes&#xd;
server: cloudflare&#xd;
cf-ray: 7b6376fefa60e976-DFW</responseHeaders>
    <record-html-infos extractorRegExp="false" htmlType="0"/>
</http-action>
<http-action actionType="1" contentType="font/woff2"
    eTag="&quot;610ae35f-4d48&quot;" extractorInjectPathPolicy="2"
    extractorPathPolicy="1" followRedirects="false"
    generatedByClient="false"
    lastModified="Wed, 04 Aug 2021 18:58:39 GMT"
    linkExtractorSeveralMatchOccurrence="1"
    linkExtractorSeveralMatchPolicy="1" linkExtractorType="6"
    method="GET"
    name="/releases/v5.15.4/webfonts/pro-fa-solid-900-5.0.0.woff2"
    path="/releases/v5.15.4/webfonts/pro-fa-solid-900-5.0.0.woff2"
    postType="6"
    recordedArtifactZipFileName="team/vus/@prism@h@r_@company_@details_@c4484560_@april/%resources%/recorded-artifacts/db02022a-1a46-48f4-bc30-a96130b7e861.zip"
    recordedResponseCode="200" responseSize="0"
    serverUid="imported_ka-p.fontawesome.com" slaProfileEnabled="false"
    uid="2b473cde-dc06-461c-a75f-ed815ef54788" useKeepAlive="false">
    <requestContentFileDescription>recorded-requests/req_09bb5d94-4537-4c62-8599-16590efe0fdd.txt</requestContentFileDescription>
    <header name="sec-fetch-mode" value="cors"/>
    <header name="referer" value="https://qaphr998two.prismhr.com/"/>
    <header name="sec-ch-ua" value="&quot;Not_A Brand&quot;;v=&quot;99&quot;, &quot;Google Chrome&quot;;v=&quot;109&quot;, &quot;Chromium&quot;;v=&quot;109&quot;"/>
    <header name="sec-fetch-site" value="cross-site"/>
    <header name="sec-ch-ua-mobile" value="?0"/>
    <header name="accept-language" value="en-US,en;q=0.9"/>
    <header name="sec-ch-ua-platform" value="&quot;Windows&quot;"/>
    <header name="origin" value="https://qaphr998two.prismhr.com"/>
    <header name="accept-encoding" value="gzip, deflate, br"/>
    <header name="sec-fetch-dest" value="font"/>
    <header name="accept" value="*/*"/>
    <header name="user-agent" value="Mozilla/5.0 (Windows NT 10.0; Win64; x64) AppleWebKit/537.36 (KHTML, like Gecko) Chrome/109.0.0.0 Safari/537.36"/>
    <responseHeaders>HTTP/2.0 200&#xd;
date: Tue, 11 Apr 2023 13:09:35 GMT&#xd;
content-type: font/woff2&#xd;
content-length: 19784&#xd;
access-control-allow-origin: *&#xd;
cache-control: max-age=31556926&#xd;
etag: "610ae35f-4d48"&#xd;
last-modified: Wed, 04 Aug 2021 18:58:39 GMT&#xd;
vary: Origin, Accept-Encoding, Access-Control-Request-Headers, Access-Control-Request-Method&#xd;
cf-cache-status: MISS&#xd;
accept-ranges: bytes&#xd;
server: cloudflare&#xd;
cf-ray: 7b6376fefa61e976-DFW</responseHeaders>
    <record-html-infos extractorRegExp="false" htmlType="0"/>
</http-action>
<http-action actionType="1" contentType="image/png"
    eTag="&quot;0311d251467ce1:0&quot;" extractorInjectPathPolicy="2"
    extractorPathPolicy="1" followRedirects="false"
    generatedByClient="false"
    lastModified="Wed, 12 Jun 2013 02:25:46 GMT"
    linkExtractorSeveralMatchOccurrence="1"
    linkExtractorSeveralMatchPolicy="1" linkExtractorType="6"
    method="GET" name="/qaphr998two/images/SuperBatchV1/Post.png"
    path="/qaphr998two/images/SuperBatchV1/Post.png" postType="6"
    recordedArtifactZipFileName="team/vus/@prism@h@r_@company_@details_@c4484560_@april/%resources%/recorded-artifacts/db02022a-1a46-48f4-bc30-a96130b7e861.zip"
    recordedResponseCode="200" responseSize="0"
    serverUid="qaphr998two.prismhr.com" slaProfileEnabled="false"
    uid="abe57029-dd55-4ab6-a761-2b0a9394ebd5" useKeepAlive="false">
    <requestContentFileDescription>recorded-requests/req_956d3d3f-003a-4261-9bcc-5f6ec16c4432.txt</requestContentFileDescription>
    <header name="Accept" value="image/avif,image/webp,image/apng,image/svg+xml,image/*,*/*;q=0.8"/>
    <header name="Accept-Encoding" value="gzip, deflate, br"/>
    <header name="Accept-Language" value="en-US,en;q=0.9"/>
    <header name="Connection" value="keep-alive"/>
    <header name="Cookie" value="DesignBAIS=machine=KAWXLIBYIGQPWGBQKBSPWVMNSQVYWBPGTBKEZDQVGXNCXKR&amp;pooler=862&amp;ver=40; IDBrowser=${IDBrowser}"/>
    <header name="Host" value="qaphr998two.prismhr.com"/>
    <header name="Referer" value="https://qaphr998two.prismhr.com/qaphr998two/"/>
    <header name="sec-ch-ua" value="&quot;Not_A Brand&quot;;v=&quot;99&quot;, &quot;Google Chrome&quot;;v=&quot;109&quot;, &quot;Chromium&quot;;v=&quot;109&quot;"/>
    <header name="sec-ch-ua-mobile" value="?0"/>
    <header name="sec-ch-ua-platform" value="&quot;Windows&quot;"/>
    <header name="Sec-Fetch-Dest" value="image"/>
    <header name="Sec-Fetch-Mode" value="no-cors"/>
    <header name="Sec-Fetch-Site" value="same-origin"/>
    <header name="User-Agent" value="Mozilla/5.0 (Windows NT 10.0; Win64; x64) AppleWebKit/537.36 (KHTML, like Gecko) Chrome/109.0.0.0 Safari/537.36"/>
    <responseHeaders>HTTP/1.1 200 OK&#xd;
Cache-Control: max-age=172800&#xd;
Content-Type: image/png&#xd;
Last-Modified: Wed, 12 Jun 2013 02:25:46 GMT&#xd;
Accept-Ranges: bytes&#xd;
ETag: "0311d251467ce1:0"&#xd;
Server: Microsoft-IIS/10.0&#xd;
X-Powered-By: ASP.NET&#xd;
Date: Tue, 11 Apr 2023 13:09:35 GMT&#xd;
Content-Length: 1229</responseHeaders>
    <record-html-infos extractorRegExp="false" htmlType="0"/>
</http-action>
<http-action actionType="1" contentType="image/png"
    eTag="&quot;0311d251467ce1:0&quot;" extractorInjectPathPolicy="2"
    extractorPathPolicy="1" followRedirects="false"
    generatedByClient="false"
    lastModified="Wed, 12 Jun 2013 02:25:46 GMT"
    linkExtractorSeveralMatchOccurrence="1"
    linkExtractorSeveralMatchPolicy="1" linkExtractorType="6"
    method="GET" name="/qaphr998two/images/vision/refresh.png"
    path="/qaphr998two/images/vision/refresh.png" postType="6"
    recordedArtifactZipFileName="team/vus/@prism@h@r_@company_@details_@c4484560_@april/%resources%/recorded-artifacts/db02022a-1a46-48f4-bc30-a96130b7e861.zip"
    recordedResponseCode="200" responseSize="0"
    serverUid="qaphr998two.prismhr.com" slaProfileEnabled="false"
    uid="341aca85-71b7-428c-ba2a-687a3486e17d" useKeepAlive="false">
    <requestContentFileDescription>recorded-requests/req_e824b1f1-e320-4e1c-8b3b-53c4225beafd.txt</requestContentFileDescription>
    <header name="Accept" value="image/avif,image/webp,image/apng,image/svg+xml,image/*,*/*;q=0.8"/>
    <header name="Accept-Encoding" value="gzip, deflate, br"/>
    <header name="Accept-Language" value="en-US,en;q=0.9"/>
    <header name="Connection" value="keep-alive"/>
    <header name="Cookie" value="DesignBAIS=machine=KAWXLIBYIGQPWGBQKBSPWVMNSQVYWBPGTBKEZDQVGXNCXKR&amp;pooler=862&amp;ver=40; IDBrowser=${IDBrowser}"/>
    <header name="Host" value="qaphr998two.prismhr.com"/>
    <header name="Referer" value="https://qaphr998two.prismhr.com/qaphr998two/"/>
    <header name="sec-ch-ua" value="&quot;Not_A Brand&quot;;v=&quot;99&quot;, &quot;Google Chrome&quot;;v=&quot;109&quot;, &quot;Chromium&quot;;v=&quot;109&quot;"/>
    <header name="sec-ch-ua-mobile" value="?0"/>
    <header name="sec-ch-ua-platform" value="&quot;Windows&quot;"/>
    <header name="Sec-Fetch-Dest" value="image"/>
    <header name="Sec-Fetch-Mode" value="no-cors"/>
    <header name="Sec-Fetch-Site" value="same-origin"/>
    <header name="User-Agent" value="Mozilla/5.0 (Windows NT 10.0; Win64; x64) AppleWebKit/537.36 (KHTML, like Gecko) Chrome/109.0.0.0 Safari/537.36"/>
    <responseHeaders>HTTP/1.1 200 OK&#xd;
Cache-Control: max-age=172800&#xd;
Content-Type: image/png&#xd;
Last-Modified: Wed, 12 Jun 2013 02:25:46 GMT&#xd;
Accept-Ranges: bytes&#xd;
ETag: "0311d251467ce1:0"&#xd;
Server: Microsoft-IIS/10.0&#xd;
X-Powered-By: ASP.NET&#xd;
Date: Tue, 11 Apr 2023 13:09:35 GMT&#xd;
Content-Length: 2062</responseHeaders>
    <record-html-infos extractorRegExp="false" htmlType="0"/>
</http-action>
<http-action actionType="1" contentType="image/gif"
    eTag="&quot;09b69cde3e9cc1:0&quot;" extractorInjectPathPolicy="2"
    extractorPathPolicy="1" followRedirects="false"
    generatedByClient="false"
    lastModified="Mon, 13 Feb 2012 00:09:50 GMT"
    linkExtractorSeveralMatchOccurrence="1"
    linkExtractorSeveralMatchPolicy="1" linkExtractorType="6"
    method="GET" name="/qaphr998two/images/vision/tphidebenactions.gif"
    path="/qaphr998two/images/vision/tphidebenactions.gif" postType="6"
    recordedArtifactZipFileName="team/vus/@prism@h@r_@company_@details_@c4484560_@april/%resources%/recorded-artifacts/db02022a-1a46-48f4-bc30-a96130b7e861.zip"
    recordedResponseCode="200" responseSize="0"
    serverUid="qaphr998two.prismhr.com" slaProfileEnabled="false"
    uid="460937d8-0ed2-44b0-8e08-13ff56478e20" useKeepAlive="false">
    <requestContentFileDescription>recorded-requests/req_007ffdd8-1590-41df-8a68-13cc460f7b26.txt</requestContentFileDescription>
    <header name="Accept" value="image/avif,image/webp,image/apng,image/svg+xml,image/*,*/*;q=0.8"/>
    <header name="Accept-Encoding" value="gzip, deflate, br"/>
    <header name="Accept-Language" value="en-US,en;q=0.9"/>
    <header name="Connection" value="keep-alive"/>
    <header name="Cookie" value="DesignBAIS=machine=KAWXLIBYIGQPWGBQKBSPWVMNSQVYWBPGTBKEZDQVGXNCXKR&amp;pooler=862&amp;ver=40; IDBrowser=${IDBrowser}"/>
    <header name="Host" value="qaphr998two.prismhr.com"/>
    <header name="Referer" value="https://qaphr998two.prismhr.com/qaphr998two/"/>
    <header name="sec-ch-ua" value="&quot;Not_A Brand&quot;;v=&quot;99&quot;, &quot;Google Chrome&quot;;v=&quot;109&quot;, &quot;Chromium&quot;;v=&quot;109&quot;"/>
    <header name="sec-ch-ua-mobile" value="?0"/>
    <header name="sec-ch-ua-platform" value="&quot;Windows&quot;"/>
    <header name="Sec-Fetch-Dest" value="image"/>
    <header name="Sec-Fetch-Mode" value="no-cors"/>
    <header name="Sec-Fetch-Site" value="same-origin"/>
    <header name="User-Agent" value="Mozilla/5.0 (Windows NT 10.0; Win64; x64) AppleWebKit/537.36 (KHTML, like Gecko) Chrome/109.0.0.0 Safari/537.36"/>
    <responseHeaders>HTTP/1.1 200 OK&#xd;
Cache-Control: max-age=172800&#xd;
Content-Type: image/gif&#xd;
Last-Modified: Mon, 13 Feb 2012 00:09:50 GMT&#xd;
Accept-Ranges: bytes&#xd;
ETag: "09b69cde3e9cc1:0"&#xd;
Server: Microsoft-IIS/10.0&#xd;
X-Powered-By: ASP.NET&#xd;
Date: Tue, 11 Apr 2023 13:09:35 GMT&#xd;
Content-Length: 79</responseHeaders>
    <record-html-infos extractorRegExp="false" htmlType="0"/>
</http-action>
