<http-page executeResourcesDynamically="false"
    name="/apis/obbe/rest2/qaphr998two/OBBE.FIND.APPROVAL.POLICY/null"
    playRequestsSequentially="true"
    recordedArtifactZipFileName="team/vus/@o@b_@standard_@c4484603/%resources%/recorded-artifacts/753133f4-930b-4a03-92d1-ec4a8e1e3409.zip"
    slaProfileEnabled="false" thinkTime="5000"
    thinkTimeMode="MODE_SIMPLE_THINK_TIME" thinkTimeRangeEnd=""
    thinkTimeRangeStart="" uid="753133f4-930b-4a03-92d1-ec4a8e1e3409">
    <embedded-action>15d472c7-2d65-4ca6-84f5-c40992a83f22</embedded-action>
    <embedded-action>a65ca5a8-86ab-4380-a5b1-c817035b6f2c</embedded-action>
    <embedded-action>27e0b8ac-d2e2-4dcd-b87a-b41c2920e4f6</embedded-action>
    <embedded-action>0e2c6e53-ac49-4578-bd5d-2062b1c135ad</embedded-action>
    <embedded-action>c9b15b3b-86d9-49a2-8b68-14cceb59a4f8</embedded-action>
    <embedded-action>1790e61e-50df-4965-b9eb-ee4c24119b50</embedded-action>
    <embedded-action>8de5dd7b-4673-4f39-9752-a195236b0a00</embedded-action>
</http-page>
<http-action actionType="1"
    contentType="application/json; charset=utf-8"
    eTag="W/&quot;87-O9y8+Romdt1IbVsKEaKaZJP9Dfo&quot;"
    extractorInjectPathPolicy="2" extractorPathPolicy="1"
    followRedirects="false" generatedByClient="false"
    linkExtractorSeveralMatchOccurrence="1"
    linkExtractorSeveralMatchPolicy="1" linkExtractorType="6"
    method="POST"
    name="/apis/obbe/rest2/qaphr998two/OBBE.FIND.APPROVAL.POLICY/null"
    path="/apis/obbe/rest2/qaphr998two/OBBE.FIND.APPROVAL.POLICY/null"
    postType="4"
    recordedArtifactZipFileName="team/vus/@o@b_@standard_@c4484603/%resources%/recorded-artifacts/753133f4-930b-4a03-92d1-ec4a8e1e3409.zip"
    recordedResponseCode="200" responseSize="135"
    serverUid="qaphr998two-ep.prismhr.com" slaProfileEnabled="false"
    uid="15d472c7-2d65-4ca6-84f5-c40992a83f22" useKeepAlive="false">
    <responsePageFileDescription>recorded-responses/res_15d472c7-2d65-4ca6-84f5-c40992a83f22</responsePageFileDescription>
    <requestContentFileDescription>recorded-requests/req_15d472c7-2d65-4ca6-84f5-c40992a83f22.txt</requestContentFileDescription>
    <header name="Accept" value="application/json"/>
    <header name="Accept-Encoding" value="gzip, deflate, br"/>
    <header name="Accept-Language" value="en-US,en;q=0.9"/>
    <header name="Access-Control-Allow-Methods" value="POST, GET, OPTIONS, PUT"/>
    <header name="Access-Control-Allow-Origin" value="*"/>
    <header name="Connection" value="keep-alive"/>
    <header name="Content-Type" value="application/json"/>
    <header name="Cookie" value="ESSauthToken=${ESSauthToken}; peoId=qaphr998two; accountId=qaphr998two; sails.sid=${sails_sid}; token=${Token}"/>
    <header name="Host" value="qaphr998two-ep.prismhr.com"/>
    <header name="Origin" value="https://qaphr998two-ep.prismhr.com"/>
    <header name="Referer" value="https://qaphr998two-ep.prismhr.com/obbe/"/>
    <header name="sec-ch-ua" value="&quot;Not_A Brand&quot;;v=&quot;99&quot;, &quot;Google Chrome&quot;;v=&quot;109&quot;, &quot;Chromium&quot;;v=&quot;109&quot;"/>
    <header name="sec-ch-ua-mobile" value="?0"/>
    <header name="sec-ch-ua-platform" value="&quot;Windows&quot;"/>
    <header name="Sec-Fetch-Dest" value="empty"/>
    <header name="Sec-Fetch-Mode" value="cors"/>
    <header name="Sec-Fetch-Site" value="same-origin"/>
    <header name="User-Agent" value="Mozilla/5.0 (Windows NT 10.0; Win64; x64) AppleWebKit/537.36 (KHTML, like Gecko) Chrome/109.0.0.0 Safari/537.36"/>
    <responseHeaders>HTTP/1.1 200 OK&#xd;
Date: Tue, 02 May 2023 09:59:48 GMT&#xd;
Content-Type: application/json; charset=utf-8&#xd;
Content-Length: 135&#xd;
Connection: keep-alive&#xd;
X-Powered-By: Express&#xd;
Access-Control-Allow-Origin: *&#xd;
requestId: d3fc4abcb8e0873e019e0645f2a26bbb&#xd;
sessionId: t-IoDWefKdN-33D0_gmerQnLsU-ilmnd&#xd;
ETag: W/"87-O9y8+Romdt1IbVsKEaKaZJP9Dfo"&#xd;
Strict-Transport-Security: max-age=31536000; includeSubDomains&#xd;
Access-Control-Allow-Origin: https://qaphr998two-ep.prismhr.com&#xd;
Access-Control-Allow-Methods: POST, PUT, PATCH, DELETE, GET, OPTIONS, HEAD&#xd;
Access-Control-Allow-Headers: Origin, X-Requested-With, Content-Type, Accept&#xd;
Access-Control-Allow-Credentials: true</responseHeaders>
    <record-html-infos extractorRegExp="false" htmlType="0"/>
    <textPostContent><![CDATA[{"clientId":"${clientId}","approvalType":"I9","account":"qaphr998two","peoId":"phr"}]]></textPostContent>
</http-action>
<http-action actionType="1"
    contentType="application/json; charset=utf-8"
    eTag="W/&quot;965-PU27a2KjctQLjqeEMdTbojgPgL4&quot;"
    extractorInjectPathPolicy="2" extractorPathPolicy="1"
    followRedirects="false" generatedByClient="false"
    linkExtractorSeveralMatchOccurrence="1"
    linkExtractorSeveralMatchPolicy="1" linkExtractorType="6"
    method="POST"
    name="/apis/obbe/rest2/qaphr998two/PREHIRE.RS.ONBOARD.DETAILS/SAVE_WORKFLOW"
    path="/apis/obbe/rest2/qaphr998two/PREHIRE.RS.ONBOARD.DETAILS/SAVE_WORKFLOW"
    postCharset="" postType="4"
    recordedArtifactZipFileName="team/vus/@o@b_@standard_@c4484603/%resources%/recorded-artifacts/753133f4-930b-4a03-92d1-ec4a8e1e3409.zip"
    recordedResponseCode="200" responseSize="2405"
    serverUid="qaphr998two-ep.prismhr.com" slaProfileEnabled="false"
    uid="a65ca5a8-86ab-4380-a5b1-c817035b6f2c" useKeepAlive="false">
    <responsePageFileDescription>recorded-responses/res_a65ca5a8-86ab-4380-a5b1-c817035b6f2c.0</responsePageFileDescription>
    <requestContentFileDescription>recorded-requests/req_a65ca5a8-86ab-4380-a5b1-c817035b6f2c.txt</requestContentFileDescription>
    <variable-extractor assertionOnNoMatch="true"
        defaultValue="&lt;NOT FOUND>" displayMode="1" endsWithSimple=""
        extractFromVarNameAdv="" extractFromVarNameSimple=""
        extractType="0" extractTypeAdv="0" extractTypeSimple="0"
        matchNumber="1" matchNumberAdv="1" matchNumberSimple="1"
        name="CS5" regExp="&quot;checksum\\?&quot;:(.*?),"
        regExpAdv="&quot;checksum\\?&quot;:(.*?),"
        setDefaultValue="true" startsWithSimple="" template="$1$"
        templateAdv="$1$" uid="7c0cd3d5-3a3d-4c44-824c-c601ccb334f5" xpath=""/>
    <variable-extractor assertionOnNoMatch="true"
        defaultValue="&lt;NOT FOUND>" displayMode="1" endsWithSimple=""
        extractFromVarNameAdv="" extractFromVarNameSimple=""
        extractType="0" extractTypeAdv="0" extractTypeSimple="0"
        matchNumber="1" matchNumberAdv="1" matchNumberSimple="1"
        name="CS5" regExp="&quot;checksum\\?&quot;:(.*?),"
        regExpAdv="&quot;checksum\\?&quot;:(.*?),"
        setDefaultValue="true" startsWithSimple="" template="$1$"
        templateAdv="$1$" uid="a2afdebd-c7d9-4378-8c59-92fe114acacb" xpath=""/>
    <variable-extractor assertionOnNoMatch="true"
        defaultValue="&lt;NOT FOUND>" displayMode="0" endsWithSimple=""
        extractFromVarNameAdv="" extractFromVarNameSimple=""
        extractType="4" extractTypeAdv="0" extractTypeSimple="4"
        jsonpath="$.response.workflow.prehireId" matchNumber="1"
        matchNumberAdv="1" matchNumberSimple="1" name="PreHire_ID"
        refererUid="ad287e79-701c-4a01-8711-1a06769a598a" regExp="(.*)"
        regExpAdv="" setDefaultValue="true" startsWithSimple=""
        template="$1$" templateAdv="$1$"
        uid="e93bc584-231e-4c63-adce-3740dcbff6fe" xpath="">
        <variable-extractor-group extract="true" occurs="1" pattern="" type="4"/>
    </variable-extractor>
    <header name="Accept" value="application/json"/>
    <header name="Accept-Encoding" value="gzip, deflate, br"/>
    <header name="Accept-Language" value="en-US,en;q=0.9"/>
    <header name="Access-Control-Allow-Methods" value="POST, GET, OPTIONS, PUT"/>
    <header name="Access-Control-Allow-Origin" value="*"/>
    <header name="Connection" value="keep-alive"/>
    <header name="Content-Type" value="application/json"/>
    <header name="Cookie" value="ESSauthToken=${ESSauthToken}; peoId=qaphr998two; accountId=qaphr998two; sails.sid=${sails_sid}; token=${Token}"/>
    <header name="Host" value="qaphr998two-ep.prismhr.com"/>
    <header name="Origin" value="https://qaphr998two-ep.prismhr.com"/>
    <header name="Referer" value="https://qaphr998two-ep.prismhr.com/obbe/"/>
    <header name="sec-ch-ua" value="&quot;Not_A Brand&quot;;v=&quot;99&quot;, &quot;Google Chrome&quot;;v=&quot;109&quot;, &quot;Chromium&quot;;v=&quot;109&quot;"/>
    <header name="sec-ch-ua-mobile" value="?0"/>
    <header name="sec-ch-ua-platform" value="&quot;Windows&quot;"/>
    <header name="Sec-Fetch-Dest" value="empty"/>
    <header name="Sec-Fetch-Mode" value="cors"/>
    <header name="Sec-Fetch-Site" value="same-origin"/>
    <header name="User-Agent" value="Mozilla/5.0 (Windows NT 10.0; Win64; x64) AppleWebKit/537.36 (KHTML, like Gecko) Chrome/109.0.0.0 Safari/537.36"/>
    <responseHeaders>HTTP/1.1 200 OK&#xd;
Date: Tue, 02 May 2023 09:59:48 GMT&#xd;
Content-Type: application/json; charset=utf-8&#xd;
Content-Length: 2405&#xd;
Connection: keep-alive&#xd;
X-Powered-By: Express&#xd;
Access-Control-Allow-Origin: *&#xd;
requestId: 09b0b2fe48f89714b72debc3cc5a7fb4&#xd;
sessionId: t-IoDWefKdN-33D0_gmerQnLsU-ilmnd&#xd;
ETag: W/"965-P1VdPw5z9CXIaNXvR67ooeL67wE"&#xd;
Strict-Transport-Security: max-age=31536000; includeSubDomains&#xd;
Access-Control-Allow-Origin: https://qaphr998two-ep.prismhr.com&#xd;
Access-Control-Allow-Methods: POST, PUT, PATCH, DELETE, GET, OPTIONS, HEAD&#xd;
Access-Control-Allow-Headers: Origin, X-Requested-With, Content-Type, Accept&#xd;
Access-Control-Allow-Credentials: true</responseHeaders>
    <record-html-infos extractorRegExp="false" htmlType="0"/>
    <textPostContent><![CDATA[{"prehireId":"${PreHire_ID}","workflow":{"prehireId":"${PreHire_ID}","wftId":"Sam_OB_WF.1.2","status":"","effectiveDate":"2019-05-10","hireDate":"2023-04-26","workflowDueDate":"2023-04-28","workflowCompletedDate":"","ssnRequired":"0","checksum":"${CS5}","prehireEmployeeId":"${Employee_ID}","clientId":"${clientId}","enableI9SupportingDocs":"Y","daysDueI9":"-6","daysDueWorkflow":"-4","enableBeAfterSubmit":"N","electronicConsent":"","createDate":"2023-04-26","prehireStatus":"","closeDate":"","forms":[{"formId":"INITIAL_VISIT.1.0","formName":"Initial Visit","status":"","usage":"OB_INITIAL_VISIT","offerType":"INITIAL_VISIT","completeDate":"","dueDate":"2023-04-28"},{"formId":"RETURN_VISIT.1.0","formName":"Return Visit","status":"","usage":"OB_RETURN_VISIT","offerType":"RETURN_VISIT","completeDate":"","dueDate":"2023-04-28"},{"formId":"I9_SECTION_ONE.1.0","formName":"I-9","status":"S","usage":"OB_I9_SECTION_ONE","offerType":"I9_SECTION_ONE","completeDate":"2023-05-2","dueDate":"2023-04-26","pdfUuid":"","pdfError":""},{"formId":"EMPLOYEE_INFORMATION.1.0","formName":"Employee Information","status":"","usage":"OB_EMPLOYEE_INFORMATION","offerType":"EMPLOYEE_INFORMATION","completeDate":"","dueDate":"2023-04-26"},{"formId":"DIRECT_DEPOSIT.1.0","formName":"Direct Deposit","status":"","usage":"OB_FORM_DIRECT_DEPOSIT","offerType":"DIRECT_DEPOSIT","completeDate":"","dueDate":"2023-04-28"},{"formId":"DISABILITY.1.0","formName":"Disability","status":"","usage":"OB_FORM_DISABILITY","offerType":"DISABILITY","completeDate":"","dueDate":"2023-04-28"},{"formId":"EEO.1.0","formName":"Race/Ethnicity","status":"","usage":"OB_FORM_EEO","offerType":"EEO","completeDate":"","dueDate":"2023-04-28"},{"formId":"VETERAN_STATUS.1.0","formName":"Veteran Status","status":"","usage":"OB_FORM_VETERAN","offerType":"VETERAN","completeDate":"","dueDate":"2023-04-28"},{"formId":"I9_SECTION_TWO.1.0","formName":"I-9 Section 2","status":"","usage":"OB_I9_SECTION_TWO","offerType":"I9_SECTION_TWO","completeDate":"","dueDate":"2023-04-29"},{"formId":"ONBOARDING_SUMMARY.1.0","formName":"Onboarding Summary","status":"","usage":"OB_SUMMARY","offerType":"ONBOARDING_SUMMARY","completeDate":"","dueDate":"2023-04-28"},{"formId":"ONBOARDING_SUBMIT.1.0","formName":"Submit","status":"","usage":"OB_SUBMIT","offerType":"ONBOARDING_SUBMIT","completeDate":"","dueDate":"2023-04-28"}],"tax":{"taxFileUUID":[]},"identity":{"i9LastName":"${OB_812.lastn}","i9FirstName":"Jim","i9MiddleInitial":"j","i9OtherLastName":"N/A","i9Address":"100 Harvard Dr","i9AptNumber":"N/A","i9City":"Dalton","i9State":"GA","i9Zip":"30720","i9BirthDate":"1973-07-05","i9SSN":"${OB_812.ssn}","i9Email":"a@bo.com","i9Phone":"(555) 555-5555","i9CitizenStatus":"Z01","i9AlienRegNo":"","i9AlienTypeNo":"","i9AlienExpDate":"N/A","i9FormI94No":"","i9ForeignPassportNo":"","i9CountryIssuance":"","i9EmployeeSignature":"","i9PreparerUsed":"N","i9NumberOfPreparers":"","i9PrismVersion":"","i9DocumentToProvide":"","i9EmployeeSignDate":"2023-05-02","i9MgrDenyReason":"","i9ApprovalId":"","i9FileUUID":[],"i9UseSupportingDocs":"N","i9SupportingDocs":{"code":[],"uuid":[]},"approvalPolicy":"","signature":true,"todayDate":"2023-05-02T09:58:06.982Z","fullName":"Jim j ${OB_812.lastn}"},"employee":{"firstName":"Jim","middleName":"J","lastName":"${OB_812.lastn}","nickname":"","birthDate":"1973-07-05","gender":"M","maritalStatus":"S","personalEmail":"a@bo.com","homePhone":"(555) 555-5555","mobilePhone":"(555) 555-5555","ssn":"${OB_812.ssn}","eeSymGeocode":"","eeAddress1":"100 Harvard Dr","eeAddress2":"","eeZip":"30720","eeZip4":"","eeCity":"Dalton","eeCounty":"","eeState":"GA","mailAddress1":"","mailAddress2":"","mailZip":"","mailZip4":"","mailCity":"","mailState":"","mailUseResident":"","residentAddressSearch":"","latitude":"","longitude":"","transitCode":"","transitName":"","schoolDistrictCode":"","schoolDistrictName":"","psdCode":"","psdRate":"","municipalityCode":"","municipalityName":"","eeVertexGeocode":"","ethnicCode":"C","eeDisabled":"","veteranStatus":"","vietnamVet":"","disabledVet":"","recentSepVet":"","servMedalVet":"","othProtVet":"","aDutyBadgeVet":"","genderDesignation":"","preferredPronoun":"","emergencyContacts":[],"lockedFields":{"firstName":"1","lastName":"1","birthDate":"1","social":"1"},"requiredFields":{}}},"account":"qaphr998two","peoId":"phr"}]]></textPostContent>
</http-action>
<http-action actionType="1"
    contentType="application/json; charset=utf-8"
    eTag="W/&quot;106e-Gli8w0ESN8u1xncPpQ263wqt9N4&quot;"
    extractorInjectPathPolicy="2" extractorPathPolicy="1"
    followRedirects="false" generatedByClient="false"
    linkExtractorSeveralMatchOccurrence="1"
    linkExtractorSeveralMatchPolicy="1" linkExtractorType="6"
    method="POST"
    name="/apis/obbe/rest2/qaphr998two/PREHIRE.RS.ONBOARD.DETAILS/SAVE_I9_SECTION1"
    path="/apis/obbe/rest2/qaphr998two/PREHIRE.RS.ONBOARD.DETAILS/SAVE_I9_SECTION1"
    postCharset="" postType="4"
    recordedArtifactZipFileName="team/vus/@o@b_@standard_@c4484603/%resources%/recorded-artifacts/753133f4-930b-4a03-92d1-ec4a8e1e3409.zip"
    recordedResponseCode="200" responseSize="4206"
    serverUid="qaphr998two-ep.prismhr.com" slaProfileEnabled="false"
    uid="27e0b8ac-d2e2-4dcd-b87a-b41c2920e4f6" useKeepAlive="false">
    <responsePageFileDescription>recorded-responses/res_27e0b8ac-d2e2-4dcd-b87a-b41c2920e4f6.0</responsePageFileDescription>
    <requestContentFileDescription>recorded-requests/req_27e0b8ac-d2e2-4dcd-b87a-b41c2920e4f6.txt</requestContentFileDescription>
    <variable-extractor assertionOnNoMatch="true"
        defaultValue="&lt;NOT FOUND>" displayMode="1" endsWithSimple=""
        extractFromVarNameAdv="" extractFromVarNameSimple=""
        extractType="0" extractTypeAdv="0" extractTypeSimple="0"
        matchNumber="1" matchNumberAdv="1" matchNumberSimple="1"
        name="CS5" regExp="&quot;checksum\\?&quot;:(.*?),"
        regExpAdv="&quot;checksum\\?&quot;:(.*?),"
        setDefaultValue="true" startsWithSimple="" template="$1$"
        templateAdv="$1$" uid="9c8e1ad9-13e0-4c4d-970c-bb9f74c019d6" xpath=""/>
    <variable-extractor assertionOnNoMatch="true"
        defaultValue="&lt;NOT FOUND>" displayMode="1" endsWithSimple=""
        extractFromVarNameAdv="" extractFromVarNameSimple=""
        extractType="0" extractTypeAdv="0" extractTypeSimple="0"
        matchNumber="1" matchNumberAdv="1" matchNumberSimple="1"
        name="CS5" regExp="&quot;checksum\\?&quot;:(.*?),"
        regExpAdv="&quot;checksum\\?&quot;:(.*?),"
        setDefaultValue="true" startsWithSimple="" template="$1$"
        templateAdv="$1$" uid="a2afdebd-c7d9-4378-8c59-92fe114acacb" xpath=""/>
    <variable-extractor assertionOnNoMatch="true"
        defaultValue="&lt;NOT FOUND>" displayMode="0" endsWithSimple=""
        extractFromVarNameAdv="" extractFromVarNameSimple=""
        extractType="4" extractTypeAdv="0" extractTypeSimple="4"
        jsonpath="$.response.workflow.prehireId" matchNumber="1"
        matchNumberAdv="1" matchNumberSimple="1" name="PreHire_ID"
        refererUid="ad287e79-701c-4a01-8711-1a06769a598a" regExp="(.*)"
        regExpAdv="" setDefaultValue="true" startsWithSimple=""
        template="$1$" templateAdv="$1$"
        uid="e93bc584-231e-4c63-adce-3740dcbff6fe" xpath="">
        <variable-extractor-group extract="true" occurs="1" pattern="" type="4"/>
    </variable-extractor>
    <header name="Accept" value="application/json"/>
    <header name="Accept-Encoding" value="gzip, deflate, br"/>
    <header name="Accept-Language" value="en-US,en;q=0.9"/>
    <header name="Access-Control-Allow-Methods" value="POST, GET, OPTIONS, PUT"/>
    <header name="Access-Control-Allow-Origin" value="*"/>
    <header name="Connection" value="keep-alive"/>
    <header name="Content-Type" value="application/json"/>
    <header name="Cookie" value="ESSauthToken=${ESSauthToken}; peoId=qaphr998two; accountId=qaphr998two; sails.sid=${sails_sid}; token=${Token}"/>
    <header name="Host" value="qaphr998two-ep.prismhr.com"/>
    <header name="Origin" value="https://qaphr998two-ep.prismhr.com"/>
    <header name="Referer" value="https://qaphr998two-ep.prismhr.com/obbe/"/>
    <header name="sec-ch-ua" value="&quot;Not_A Brand&quot;;v=&quot;99&quot;, &quot;Google Chrome&quot;;v=&quot;109&quot;, &quot;Chromium&quot;;v=&quot;109&quot;"/>
    <header name="sec-ch-ua-mobile" value="?0"/>
    <header name="sec-ch-ua-platform" value="&quot;Windows&quot;"/>
    <header name="Sec-Fetch-Dest" value="empty"/>
    <header name="Sec-Fetch-Mode" value="cors"/>
    <header name="Sec-Fetch-Site" value="same-origin"/>
    <header name="User-Agent" value="Mozilla/5.0 (Windows NT 10.0; Win64; x64) AppleWebKit/537.36 (KHTML, like Gecko) Chrome/109.0.0.0 Safari/537.36"/>
    <responseHeaders>HTTP/1.1 200 OK&#xd;
Date: Tue, 02 May 2023 09:59:50 GMT&#xd;
Content-Type: application/json; charset=utf-8&#xd;
Content-Length: 4206&#xd;
Connection: keep-alive&#xd;
X-Powered-By: Express&#xd;
Access-Control-Allow-Origin: *&#xd;
requestId: 9b07f4ddb37411cb0bc03cb89b7aef56&#xd;
sessionId: t-IoDWefKdN-33D0_gmerQnLsU-ilmnd&#xd;
ETag: W/"106e-ICoNB2T0RGj0T/TOMWEFLyBTuLU"&#xd;
Strict-Transport-Security: max-age=31536000; includeSubDomains&#xd;
Access-Control-Allow-Origin: https://qaphr998two-ep.prismhr.com&#xd;
Access-Control-Allow-Methods: POST, PUT, PATCH, DELETE, GET, OPTIONS, HEAD&#xd;
Access-Control-Allow-Headers: Origin, X-Requested-With, Content-Type, Accept&#xd;
Access-Control-Allow-Credentials: true</responseHeaders>
    <record-html-infos extractorRegExp="false" htmlType="0"/>
    <textPostContent><![CDATA[{"prehireId":"${PreHire_ID}","step":"I9_SECTION1","workflow":{"prehireId":"${PreHire_ID}","wftId":"Sam_OB_WF.1.2","status":"","effectiveDate":"2019-05-10","hireDate":"2023-04-26","workflowDueDate":"2023-04-28","workflowCompletedDate":"","ssnRequired":"0","checksum":"${CS5}","prehireEmployeeId":"${Employee_ID}","clientId":"${clientId}","enableI9SupportingDocs":"Y","daysDueI9":"-6","daysDueWorkflow":"-4","enableBeAfterSubmit":"N","electronicConsent":"","createDate":"2023-04-26","prehireStatus":"","closeDate":"","forms":[{"formId":"INITIAL_VISIT.1.0","formName":"Initial Visit","status":"","usage":"OB_INITIAL_VISIT","offerType":"INITIAL_VISIT","completeDate":"","dueDate":"2023-04-28"},{"formId":"RETURN_VISIT.1.0","formName":"Return Visit","status":"","usage":"OB_RETURN_VISIT","offerType":"RETURN_VISIT","completeDate":"","dueDate":"2023-04-28"},{"formId":"I9_SECTION_ONE.1.0","formName":"I-9","status":"S","usage":"OB_I9_SECTION_ONE","offerType":"I9_SECTION_ONE","completeDate":"2023-05-02","dueDate":"2023-04-26","pdfUuid":"","pdfError":""},{"formId":"EMPLOYEE_INFORMATION.1.0","formName":"Employee Information","status":"","usage":"OB_EMPLOYEE_INFORMATION","offerType":"EMPLOYEE_INFORMATION","completeDate":"","dueDate":"2023-04-26"},{"formId":"DIRECT_DEPOSIT.1.0","formName":"Direct Deposit","status":"","usage":"OB_FORM_DIRECT_DEPOSIT","offerType":"DIRECT_DEPOSIT","completeDate":"","dueDate":"2023-04-28"},{"formId":"DISABILITY.1.0","formName":"Disability","status":"","usage":"OB_FORM_DISABILITY","offerType":"DISABILITY","completeDate":"","dueDate":"2023-04-28"},{"formId":"EEO.1.0","formName":"Race/Ethnicity","status":"","usage":"OB_FORM_EEO","offerType":"EEO","completeDate":"","dueDate":"2023-04-28"},{"formId":"VETERAN_STATUS.1.0","formName":"Veteran Status","status":"","usage":"OB_FORM_VETERAN","offerType":"VETERAN","completeDate":"","dueDate":"2023-04-28"},{"formId":"I9_SECTION_TWO.1.0","formName":"I-9 Section 2","status":"","usage":"OB_I9_SECTION_TWO","offerType":"I9_SECTION_TWO","completeDate":"","dueDate":"2023-04-29"},{"formId":"ONBOARDING_SUMMARY.1.0","formName":"Onboarding Summary","status":"","usage":"OB_SUMMARY","offerType":"ONBOARDING_SUMMARY","completeDate":"","dueDate":"2023-04-28"},{"formId":"ONBOARDING_SUBMIT.1.0","formName":"Submit","status":"","usage":"OB_SUBMIT","offerType":"ONBOARDING_SUBMIT","completeDate":"","dueDate":"2023-04-28"}],"tax":{"taxFileUUID":[]},"identity":{"i9LastName":"${OB_812.lastn}","i9FirstName":"Jim","i9MiddleInitial":"j","i9OtherLastName":"N/A","i9Address":"100 Harvard Dr","i9AptNumber":"N/A","i9City":"Dalton","i9State":"GA","i9Zip":"30720","i9BirthDate":"1973-07-05","i9SSN":"${OB_812.ssn}","i9Email":"a@bo.com","i9Phone":"(555) 555-5555","i9CitizenStatus":"Z01","i9AlienRegNo":"","i9AlienTypeNo":"","i9AlienExpDate":"N/A","i9FormI94No":"","i9ForeignPassportNo":"","i9CountryIssuance":"","i9EmployeeSignature":"","i9PreparerUsed":"N","i9NumberOfPreparers":"","i9PrismVersion":"","i9DocumentToProvide":"","i9EmployeeSignDate":"2023-05-02","i9MgrDenyReason":"","i9ApprovalId":"","i9FileUUID":[],"i9UseSupportingDocs":"N","i9SupportingDocs":{"code":[],"uuid":[]},"approvalPolicy":""},"employee":{"firstName":"Jim","middleName":"J","lastName":"${OB_812.lastn}","nickname":"","birthDate":"1973-07-05","gender":"M","maritalStatus":"S","personalEmail":"a@bo.com","homePhone":"(555) 555-5555","mobilePhone":"(555) 555-5555","ssn":"${OB_812.ssn}","eeSymGeocode":"","eeAddress1":"100 Harvard Dr","eeAddress2":"","eeZip":"30720","eeZip4":"","eeCity":"Dalton","eeCounty":"","eeState":"GA","mailAddress1":"","mailAddress2":"","mailZip":"","mailZip4":"","mailCity":"","mailState":"","mailUseResident":"","residentAddressSearch":"","latitude":"","longitude":"","transitCode":"","transitName":"","schoolDistrictCode":"","schoolDistrictName":"","psdCode":"","psdRate":"","municipalityCode":"","municipalityName":"","eeVertexGeocode":"","ethnicCode":"C","eeDisabled":"","veteranStatus":"","vietnamVet":"","disabledVet":"","recentSepVet":"","servMedalVet":"","othProtVet":"","aDutyBadgeVet":"","genderDesignation":"","preferredPronoun":"","emergencyContacts":[],"lockedFields":{"firstName":"1","lastName":"1","birthDate":"1","social":"1"},"requiredFields":{}}},"account":"qaphr998two","peoId":"phr"}]]></textPostContent>
</http-action>
<http-action actionType="1"
    contentType="application/json; charset=utf-8"
    eTag="W/&quot;f15-YJJCcXN1O9oH4wuYIgmOs/ODvvA&quot;"
    extractorInjectPathPolicy="2" extractorPathPolicy="1"
    followRedirects="false" generatedByClient="false"
    linkExtractorSeveralMatchOccurrence="1"
    linkExtractorSeveralMatchPolicy="1" linkExtractorType="6"
    method="POST"
    name="/apis/obbe/rest2/qaphr998two/PREHIRE.RS.ONBOARD.DETAILS/GET_I9_SECTION2"
    path="/apis/obbe/rest2/qaphr998two/PREHIRE.RS.ONBOARD.DETAILS/GET_I9_SECTION2"
    postCharset="" postType="4"
    recordedArtifactZipFileName="team/vus/@o@b_@standard_@c4484603/%resources%/recorded-artifacts/753133f4-930b-4a03-92d1-ec4a8e1e3409.zip"
    recordedResponseCode="200" responseSize="3861"
    serverUid="qaphr998two-ep.prismhr.com" slaProfileEnabled="false"
    uid="0e2c6e53-ac49-4578-bd5d-2062b1c135ad" useKeepAlive="false">
    <responsePageFileDescription>recorded-responses/res_0e2c6e53-ac49-4578-bd5d-2062b1c135ad.0</responsePageFileDescription>
    <requestContentFileDescription>recorded-requests/req_0e2c6e53-ac49-4578-bd5d-2062b1c135ad.txt</requestContentFileDescription>
    <variable-extractor assertionOnNoMatch="true"
        defaultValue="&lt;NOT FOUND>" displayMode="1" endsWithSimple=""
        extractFromVarNameAdv="" extractFromVarNameSimple=""
        extractType="0" extractTypeAdv="0" extractTypeSimple="0"
        matchNumber="1" matchNumberAdv="1" matchNumberSimple="1"
        name="CS5" regExp="&quot;checksum\\?&quot;:(.*?),"
        regExpAdv="&quot;checksum\\?&quot;:(.*?),"
        setDefaultValue="true" startsWithSimple="" template="$1$"
        templateAdv="$1$" uid="a2afdebd-c7d9-4378-8c59-92fe114acacb" xpath=""/>
    <variable-extractor assertionOnNoMatch="true"
        defaultValue="&lt;NOT FOUND>" displayMode="0" endsWithSimple=""
        extractFromVarNameAdv="" extractFromVarNameSimple=""
        extractType="4" extractTypeAdv="0" extractTypeSimple="4"
        jsonpath="$.response.workflow.prehireId" matchNumber="1"
        matchNumberAdv="1" matchNumberSimple="1" name="PreHire_ID"
        refererUid="ad287e79-701c-4a01-8711-1a06769a598a" regExp="(.*)"
        regExpAdv="" setDefaultValue="true" startsWithSimple=""
        template="$1$" templateAdv="$1$"
        uid="e93bc584-231e-4c63-adce-3740dcbff6fe" xpath="">
        <variable-extractor-group extract="true" occurs="1" pattern="" type="4"/>
    </variable-extractor>
    <header name="Accept" value="application/json"/>
    <header name="Accept-Encoding" value="gzip, deflate, br"/>
    <header name="Accept-Language" value="en-US,en;q=0.9"/>
    <header name="Access-Control-Allow-Methods" value="POST, GET, OPTIONS, PUT"/>
    <header name="Access-Control-Allow-Origin" value="*"/>
    <header name="Connection" value="keep-alive"/>
    <header name="Content-Type" value="application/json"/>
    <header name="Cookie" value="ESSauthToken=${ESSauthToken}; peoId=qaphr998two; accountId=qaphr998two; sails.sid=${sails_sid}; token=${Token}"/>
    <header name="Host" value="qaphr998two-ep.prismhr.com"/>
    <header name="Origin" value="https://qaphr998two-ep.prismhr.com"/>
    <header name="Referer" value="https://qaphr998two-ep.prismhr.com/obbe/"/>
    <header name="sec-ch-ua" value="&quot;Not_A Brand&quot;;v=&quot;99&quot;, &quot;Google Chrome&quot;;v=&quot;109&quot;, &quot;Chromium&quot;;v=&quot;109&quot;"/>
    <header name="sec-ch-ua-mobile" value="?0"/>
    <header name="sec-ch-ua-platform" value="&quot;Windows&quot;"/>
    <header name="Sec-Fetch-Dest" value="empty"/>
    <header name="Sec-Fetch-Mode" value="cors"/>
    <header name="Sec-Fetch-Site" value="same-origin"/>
    <header name="User-Agent" value="Mozilla/5.0 (Windows NT 10.0; Win64; x64) AppleWebKit/537.36 (KHTML, like Gecko) Chrome/109.0.0.0 Safari/537.36"/>
    <responseHeaders>HTTP/1.1 200 OK&#xd;
Date: Tue, 02 May 2023 09:59:50 GMT&#xd;
Content-Type: application/json; charset=utf-8&#xd;
Content-Length: 3861&#xd;
Connection: keep-alive&#xd;
X-Powered-By: Express&#xd;
Access-Control-Allow-Origin: *&#xd;
requestId: 41ea40c36ac9d7b1748ff131c22afe70&#xd;
sessionId: t-IoDWefKdN-33D0_gmerQnLsU-ilmnd&#xd;
ETag: W/"f15-sSxsEe5jeEOLhyi+SoaxN7pX6Mw"&#xd;
Strict-Transport-Security: max-age=31536000; includeSubDomains&#xd;
Access-Control-Allow-Origin: https://qaphr998two-ep.prismhr.com&#xd;
Access-Control-Allow-Methods: POST, PUT, PATCH, DELETE, GET, OPTIONS, HEAD&#xd;
Access-Control-Allow-Headers: Origin, X-Requested-With, Content-Type, Accept&#xd;
Access-Control-Allow-Credentials: true</responseHeaders>
    <record-html-infos extractorRegExp="false" htmlType="0"/>
    <textPostContent><![CDATA[{"prehireId":"${PreHire_ID}","account":"qaphr998two","peoId":"phr"}]]></textPostContent>
</http-action>
<http-action actionType="1"
    contentType="application/json; charset=utf-8"
    eTag="W/&quot;10-6Hx/xBOiv5nxQXPPNEj3esQTBYc&quot;"
    extractorInjectPathPolicy="2" extractorPathPolicy="1"
    followRedirects="false" generatedByClient="false"
    linkExtractorSeveralMatchOccurrence="1"
    linkExtractorSeveralMatchPolicy="1" linkExtractorType="6"
    method="POST"
    name="/apis/obbe/rest2/qaphr998two/PREHIRE.RS.NOTIFY/NOTIFY"
    path="/apis/obbe/rest2/qaphr998two/PREHIRE.RS.NOTIFY/NOTIFY"
    postType="4"
    recordedArtifactZipFileName="team/vus/@o@b_@standard_@c4484603/%resources%/recorded-artifacts/753133f4-930b-4a03-92d1-ec4a8e1e3409.zip"
    recordedResponseCode="200" responseSize="16"
    serverUid="qaphr998two-ep.prismhr.com" slaProfileEnabled="false"
    uid="c9b15b3b-86d9-49a2-8b68-14cceb59a4f8" useKeepAlive="false">
    <responsePageFileDescription>recorded-responses/res_c9b15b3b-86d9-49a2-8b68-14cceb59a4f8</responsePageFileDescription>
    <requestContentFileDescription>recorded-requests/req_c9b15b3b-86d9-49a2-8b68-14cceb59a4f8.txt</requestContentFileDescription>
    <header name="Accept" value="application/json"/>
    <header name="Accept-Encoding" value="gzip, deflate, br"/>
    <header name="Accept-Language" value="en-US,en;q=0.9"/>
    <header name="Access-Control-Allow-Methods" value="POST, GET, OPTIONS, PUT"/>
    <header name="Access-Control-Allow-Origin" value="*"/>
    <header name="Connection" value="keep-alive"/>
    <header name="Content-Type" value="application/json"/>
    <header name="Cookie" value="ESSauthToken=${ESSauthToken}; peoId=qaphr998two; accountId=qaphr998two; sails.sid=${sails_sid}; token=${Token}"/>
    <header name="Host" value="qaphr998two-ep.prismhr.com"/>
    <header name="Origin" value="https://qaphr998two-ep.prismhr.com"/>
    <header name="Referer" value="https://qaphr998two-ep.prismhr.com/obbe/"/>
    <header name="sec-ch-ua" value="&quot;Not_A Brand&quot;;v=&quot;99&quot;, &quot;Google Chrome&quot;;v=&quot;109&quot;, &quot;Chromium&quot;;v=&quot;109&quot;"/>
    <header name="sec-ch-ua-mobile" value="?0"/>
    <header name="sec-ch-ua-platform" value="&quot;Windows&quot;"/>
    <header name="Sec-Fetch-Dest" value="empty"/>
    <header name="Sec-Fetch-Mode" value="cors"/>
    <header name="Sec-Fetch-Site" value="same-origin"/>
    <header name="User-Agent" value="Mozilla/5.0 (Windows NT 10.0; Win64; x64) AppleWebKit/537.36 (KHTML, like Gecko) Chrome/109.0.0.0 Safari/537.36"/>
    <responseHeaders>HTTP/1.1 200 OK&#xd;
Date: Tue, 02 May 2023 09:59:50 GMT&#xd;
Content-Type: application/json; charset=utf-8&#xd;
Content-Length: 16&#xd;
Connection: keep-alive&#xd;
X-Powered-By: Express&#xd;
Access-Control-Allow-Origin: *&#xd;
requestId: 1532517ab5f953bfe0a1c34ade789444&#xd;
sessionId: t-IoDWefKdN-33D0_gmerQnLsU-ilmnd&#xd;
ETag: W/"10-6Hx/xBOiv5nxQXPPNEj3esQTBYc"&#xd;
Strict-Transport-Security: max-age=31536000; includeSubDomains&#xd;
Access-Control-Allow-Origin: https://qaphr998two-ep.prismhr.com&#xd;
Access-Control-Allow-Methods: POST, PUT, PATCH, DELETE, GET, OPTIONS, HEAD&#xd;
Access-Control-Allow-Headers: Origin, X-Requested-With, Content-Type, Accept&#xd;
Access-Control-Allow-Credentials: true</responseHeaders>
    <record-html-infos extractorRegExp="false" htmlType="0"/>
    <textPostContent><![CDATA[{"operation":"NOTIFY","clientId":"${clientId}","prehireId":"${PreHire_ID}","triggerCondition":"EE-FORM-SUBMIT","formId":"I9_SECTION_ONE.1.0","account":"qaphr998two","peoId":"phr"}]]></textPostContent>
</http-action>
<http-action actionType="1"
    contentType="application/json; charset=utf-8"
    eTag="W/&quot;d97-b1VPXVBomiFOhIReo6Rj3KWR+Qk&quot;"
    extractorInjectPathPolicy="2" extractorPathPolicy="1"
    followRedirects="false" generatedByClient="false"
    linkExtractorSeveralMatchOccurrence="1"
    linkExtractorSeveralMatchPolicy="1" linkExtractorType="6"
    method="POST"
    name="/apis/obbe/rest2/qaphr998two/PREHIRE.RS.ONBOARD.DETAILS/GET_EMPLOYEE_INFO"
    path="/apis/obbe/rest2/qaphr998two/PREHIRE.RS.ONBOARD.DETAILS/GET_EMPLOYEE_INFO"
    postCharset="" postType="4"
    recordedArtifactZipFileName="team/vus/@o@b_@standard_@c4484603/%resources%/recorded-artifacts/753133f4-930b-4a03-92d1-ec4a8e1e3409.zip"
    recordedResponseCode="200" responseSize="3479"
    serverUid="qaphr998two-ep.prismhr.com" slaProfileEnabled="false"
    uid="1790e61e-50df-4965-b9eb-ee4c24119b50" useKeepAlive="false">
    <responsePageFileDescription>recorded-responses/res_1790e61e-50df-4965-b9eb-ee4c24119b50.0</responsePageFileDescription>
    <requestContentFileDescription>recorded-requests/req_1790e61e-50df-4965-b9eb-ee4c24119b50.txt</requestContentFileDescription>
    <variable-extractor assertionOnNoMatch="true"
        defaultValue="&lt;NOT FOUND>" displayMode="1" endsWithSimple=""
        extractFromVarNameAdv="" extractFromVarNameSimple=""
        extractType="0" extractTypeAdv="0" extractTypeSimple="0"
        matchNumber="1" matchNumberAdv="1" matchNumberSimple="1"
        name="CS5" regExp="&quot;checksum\\?&quot;:(.*?),"
        regExpAdv="&quot;checksum\\?&quot;:(.*?),"
        setDefaultValue="true" startsWithSimple="" template="$1$"
        templateAdv="$1$" uid="a2afdebd-c7d9-4378-8c59-92fe114acacb" xpath=""/>
    <variable-extractor assertionOnNoMatch="true"
        defaultValue="&lt;NOT FOUND>" displayMode="0" endsWithSimple=""
        extractFromVarNameAdv="" extractFromVarNameSimple=""
        extractType="4" extractTypeAdv="0" extractTypeSimple="4"
        jsonpath="$.response.workflow.prehireId" matchNumber="1"
        matchNumberAdv="1" matchNumberSimple="1" name="PreHire_ID"
        refererUid="ad287e79-701c-4a01-8711-1a06769a598a" regExp="(.*)"
        regExpAdv="" setDefaultValue="true" startsWithSimple=""
        template="$1$" templateAdv="$1$"
        uid="e93bc584-231e-4c63-adce-3740dcbff6fe" xpath="">
        <variable-extractor-group extract="true" occurs="1" pattern="" type="4"/>
    </variable-extractor>
    <header name="Accept" value="application/json"/>
    <header name="Accept-Encoding" value="gzip, deflate, br"/>
    <header name="Accept-Language" value="en-US,en;q=0.9"/>
    <header name="Access-Control-Allow-Methods" value="POST, GET, OPTIONS, PUT"/>
    <header name="Access-Control-Allow-Origin" value="*"/>
    <header name="Connection" value="keep-alive"/>
    <header name="Content-Type" value="application/json"/>
    <header name="Cookie" value="ESSauthToken=${ESSauthToken}; peoId=qaphr998two; accountId=qaphr998two; sails.sid=${sails_sid}; token=${Token}"/>
    <header name="Host" value="qaphr998two-ep.prismhr.com"/>
    <header name="Origin" value="https://qaphr998two-ep.prismhr.com"/>
    <header name="Referer" value="https://qaphr998two-ep.prismhr.com/obbe/"/>
    <header name="sec-ch-ua" value="&quot;Not_A Brand&quot;;v=&quot;99&quot;, &quot;Google Chrome&quot;;v=&quot;109&quot;, &quot;Chromium&quot;;v=&quot;109&quot;"/>
    <header name="sec-ch-ua-mobile" value="?0"/>
    <header name="sec-ch-ua-platform" value="&quot;Windows&quot;"/>
    <header name="Sec-Fetch-Dest" value="empty"/>
    <header name="Sec-Fetch-Mode" value="cors"/>
    <header name="Sec-Fetch-Site" value="same-origin"/>
    <header name="User-Agent" value="Mozilla/5.0 (Windows NT 10.0; Win64; x64) AppleWebKit/537.36 (KHTML, like Gecko) Chrome/109.0.0.0 Safari/537.36"/>
    <responseHeaders>HTTP/1.1 200 OK&#xd;
Date: Tue, 02 May 2023 09:59:50 GMT&#xd;
Content-Type: application/json; charset=utf-8&#xd;
Content-Length: 3479&#xd;
Connection: keep-alive&#xd;
X-Powered-By: Express&#xd;
Access-Control-Allow-Origin: *&#xd;
requestId: 641cfff6d55f44ce67b79ecd9ac7932a&#xd;
sessionId: t-IoDWefKdN-33D0_gmerQnLsU-ilmnd&#xd;
ETag: W/"d97-Y5rrBJBkCipTWGKoqgNXOLw9Wz8"&#xd;
Strict-Transport-Security: max-age=31536000; includeSubDomains&#xd;
Access-Control-Allow-Origin: https://qaphr998two-ep.prismhr.com&#xd;
Access-Control-Allow-Methods: POST, PUT, PATCH, DELETE, GET, OPTIONS, HEAD&#xd;
Access-Control-Allow-Headers: Origin, X-Requested-With, Content-Type, Accept&#xd;
Access-Control-Allow-Credentials: true</responseHeaders>
    <record-html-infos extractorRegExp="false" htmlType="0"/>
    <textPostContent><![CDATA[{"prehireId":"${PreHire_ID}","account":"qaphr998two","peoId":"phr"}]]></textPostContent>
</http-action>
<http-action actionType="1"
    contentType="application/json; charset=utf-8"
    eTag="W/&quot;2bb-vP51EFHKoaF8Oi02yBF3j4B4Hgo&quot;"
    extractorInjectPathPolicy="2" extractorPathPolicy="1"
    followRedirects="false" generatedByClient="false"
    linkExtractorSeveralMatchOccurrence="1"
    linkExtractorSeveralMatchPolicy="1" linkExtractorType="6"
    method="POST"
    name="/apis/obbe/rest2/qaphr998two/OBBE.RS.GET.GENDER.INFO/GET_PRONOUN_AND_GENDER"
    path="/apis/obbe/rest2/qaphr998two/OBBE.RS.GET.GENDER.INFO/GET_PRONOUN_AND_GENDER"
    postType="4"
    recordedArtifactZipFileName="team/vus/@o@b_@standard_@c4484603/%resources%/recorded-artifacts/753133f4-930b-4a03-92d1-ec4a8e1e3409.zip"
    recordedResponseCode="200" responseSize="699"
    serverUid="qaphr998two-ep.prismhr.com" slaProfileEnabled="false"
    uid="8de5dd7b-4673-4f39-9752-a195236b0a00" useKeepAlive="false">
    <responsePageFileDescription>recorded-responses/res_8de5dd7b-4673-4f39-9752-a195236b0a00</responsePageFileDescription>
    <requestContentFileDescription>recorded-requests/req_8de5dd7b-4673-4f39-9752-a195236b0a00.txt</requestContentFileDescription>
    <header name="Accept" value="application/json"/>
    <header name="Accept-Encoding" value="gzip, deflate, br"/>
    <header name="Accept-Language" value="en-US,en;q=0.9"/>
    <header name="Access-Control-Allow-Methods" value="POST, GET, OPTIONS, PUT"/>
    <header name="Access-Control-Allow-Origin" value="*"/>
    <header name="Connection" value="keep-alive"/>
    <header name="Content-Type" value="application/json"/>
    <header name="Cookie" value="ESSauthToken=${ESSauthToken}; peoId=qaphr998two; accountId=qaphr998two; sails.sid=${sails_sid}; token=${Token}"/>
    <header name="Host" value="qaphr998two-ep.prismhr.com"/>
    <header name="Origin" value="https://qaphr998two-ep.prismhr.com"/>
    <header name="Referer" value="https://qaphr998two-ep.prismhr.com/obbe/"/>
    <header name="sec-ch-ua" value="&quot;Not_A Brand&quot;;v=&quot;99&quot;, &quot;Google Chrome&quot;;v=&quot;109&quot;, &quot;Chromium&quot;;v=&quot;109&quot;"/>
    <header name="sec-ch-ua-mobile" value="?0"/>
    <header name="sec-ch-ua-platform" value="&quot;Windows&quot;"/>
    <header name="Sec-Fetch-Dest" value="empty"/>
    <header name="Sec-Fetch-Mode" value="cors"/>
    <header name="Sec-Fetch-Site" value="same-origin"/>
    <header name="User-Agent" value="Mozilla/5.0 (Windows NT 10.0; Win64; x64) AppleWebKit/537.36 (KHTML, like Gecko) Chrome/109.0.0.0 Safari/537.36"/>
    <responseHeaders>HTTP/1.1 200 OK&#xd;
Date: Tue, 02 May 2023 09:59:50 GMT&#xd;
Content-Type: application/json; charset=utf-8&#xd;
Content-Length: 699&#xd;
Connection: keep-alive&#xd;
X-Powered-By: Express&#xd;
Access-Control-Allow-Origin: *&#xd;
requestId: 68116b1aa9acd4237411b9ec9d04493a&#xd;
sessionId: t-IoDWefKdN-33D0_gmerQnLsU-ilmnd&#xd;
ETag: W/"2bb-vP51EFHKoaF8Oi02yBF3j4B4Hgo"&#xd;
Strict-Transport-Security: max-age=31536000; includeSubDomains&#xd;
Access-Control-Allow-Origin: https://qaphr998two-ep.prismhr.com&#xd;
Access-Control-Allow-Methods: POST, PUT, PATCH, DELETE, GET, OPTIONS, HEAD&#xd;
Access-Control-Allow-Headers: Origin, X-Requested-With, Content-Type, Accept&#xd;
Access-Control-Allow-Credentials: true</responseHeaders>
    <record-html-infos extractorRegExp="false" htmlType="0"/>
    <textPostContent><![CDATA[{"account":"qaphr998two","peoId":"phr"}]]></textPostContent>
</http-action>
