<http-page executeResourcesDynamically="false"
    name="/wave1/apis/obbe/rest2/qaphr998two/PREHIRE.RS.ONBOARD.DETAILS/SAVE_I9_SECTION1"
    playRequestsSequentially="false"
    recordedArtifactZipFileName="team/vus/@o@b_@standard_@c4484603_@march/%resources%/recorded-artifacts/25e3c35d-6095-4195-b6f9-3c295ec0f489.zip"
    slaProfileEnabled="false" thinkTime="5000"
    thinkTimeMode="MODE_SIMPLE_THINK_TIME" thinkTimeRangeEnd=""
    thinkTimeRangeStart="" uid="25e3c35d-6095-4195-b6f9-3c295ec0f489">
    <embedded-action>c4e4f304-aad3-49a4-be1c-d567ec5dae85</embedded-action>
    <embedded-action>e1031d91-d97c-4b6c-b33d-126e06c01cee</embedded-action>
    <embedded-action>c131e25e-ae95-4af6-a2d0-231cbc84c2fc</embedded-action>
</http-page>
<http-action actionType="1"
    contentType="application/json; charset=utf-8"
    eTag="W/&quot;f90-FaHcqxFMmbu4w5Ae4MgfDDwywRs&quot;"
    extractorInjectPathPolicy="2" extractorPathPolicy="1"
    followRedirects="false" generatedByClient="false"
    linkExtractorSeveralMatchOccurrence="1"
    linkExtractorSeveralMatchPolicy="1" linkExtractorType="6"
    method="POST"
    name="/wave1/apis/obbe/rest2/qaphr998two/PREHIRE.RS.ONBOARD.DETAILS/SAVE_I9_SECTION1"
    path="/wave1/apis/obbe/rest2/qaphr998two/PREHIRE.RS.ONBOARD.DETAILS/SAVE_I9_SECTION1"
    postCharset="" postType="4"
    recordedArtifactZipFileName="team/vus/@o@b_@standard_@c4484603_@march/%resources%/recorded-artifacts/25e3c35d-6095-4195-b6f9-3c295ec0f489.zip"
    recordedResponseCode="200" responseSize="3984"
    serverUid="qaphr998two-ep.prismhr.com" slaProfileEnabled="false"
    uid="c4e4f304-aad3-49a4-be1c-d567ec5dae85" useKeepAlive="false">
    <responsePageFileDescription>recorded-responses/res_e8227205-eb42-4701-a2f6-750103750931.0</responsePageFileDescription>
    <requestContentFileDescription>recorded-requests/req_e8227205-eb42-4701-a2f6-750103750931.txt</requestContentFileDescription>
    <variable-extractor assertionOnNoMatch="true"
        defaultValue="&lt;NOT FOUND>" displayMode="1" endsWithSimple=""
        extractFromVarNameAdv="" extractFromVarNameSimple=""
        extractType="0" extractTypeAdv="0" extractTypeSimple="0"
        matchNumber="1" matchNumberAdv="1" matchNumberSimple="1"
        name="CS5" regExp="&quot;checksum\\?&quot;:(.*?),"
        regExpAdv="&quot;checksum\\?&quot;:(.*?),"
        setDefaultValue="true" startsWithSimple="" template="$1$"
        templateAdv="$1$" uid="cb0b7331-7614-4d96-8ae0-b581b62caa19" xpath=""/>
    <variable-extractor assertionOnNoMatch="true"
        defaultValue="&lt;NOT FOUND>" displayMode="0" endsWithSimple=""
        extractFromVarNameAdv="" extractFromVarNameSimple=""
        extractType="4" extractTypeAdv="0" extractTypeSimple="4"
        jsonpath="$.response.workflow.prehireId" matchNumber="1"
        matchNumberAdv="1" matchNumberSimple="1" name="PreHire_ID"
        refererUid="ad287e79-701c-4a01-8711-1a06769a598a" regExp="(.*)"
        regExpAdv="" setDefaultValue="true" startsWithSimple=""
        template="$1$" templateAdv="$1$"
        uid="e93bc584-231e-4c63-adce-3740dcbff6fe" xpath="">
        <variable-extractor-group extract="true" occurs="1" pattern="" type="4"/>
    </variable-extractor>
    <header name="Accept" value="application/json"/>
    <header name="Accept-Encoding" value="gzip, deflate, br"/>
    <header name="Accept-Language" value="en-US,en;q=0.9"/>
    <header name="Access-Control-Allow-Methods" value="POST, GET, OPTIONS, PUT"/>
    <header name="Access-Control-Allow-Origin" value="*"/>
    <header name="Connection" value="keep-alive"/>
    <header name="Content-Type" value="application/json"/>
    <header name="Cookie" value="ESSauthToken=${ESSauthToken}; peoId=qaphr998two; accountId=qaphr998two; sails.sid=${sails_sid}; token=${Token}"/>
    <header name="Host" value="qaphr998two-ep.prismhr.com"/>
    <header name="Origin" value="https://qaphr998two-ep.prismhr.com"/>
    <header name="Referer" value="https://qaphr998two-ep.prismhr.com/obbe/"/>
    <header name="sec-ch-ua" value="&quot;Not_A Brand&quot;;v=&quot;99&quot;, &quot;Google Chrome&quot;;v=&quot;109&quot;, &quot;Chromium&quot;;v=&quot;109&quot;"/>
    <header name="sec-ch-ua-mobile" value="?0"/>
    <header name="sec-ch-ua-platform" value="&quot;Windows&quot;"/>
    <header name="Sec-Fetch-Dest" value="empty"/>
    <header name="Sec-Fetch-Mode" value="cors"/>
    <header name="Sec-Fetch-Site" value="same-origin"/>
    <header name="User-Agent" value="Mozilla/5.0 (Windows NT 10.0; Win64; x64) AppleWebKit/537.36 (KHTML, like Gecko) Chrome/109.0.0.0 Safari/537.36"/>
    <responseHeaders>HTTP/1.1 200 OK&#xd;
Date: Fri, 03 Mar 2023 09:55:17 GMT&#xd;
Content-Type: application/json; charset=utf-8&#xd;
Content-Length: 3984&#xd;
Connection: keep-alive&#xd;
X-Powered-By: Express&#xd;
Access-Control-Allow-Origin: *&#xd;
requestId: fd0d124ea4e8fa5f68c631b42936de83&#xd;
sessionId: rv8ppYHaH-zmnu7dgeoP-Zos5mrtEJuu&#xd;
ETag: W/"f90-5Bb+PvaO7nkpnvoNNA35GtrbvP0"&#xd;
Strict-Transport-Security: max-age=31536000; includeSubDomains&#xd;
Access-Control-Allow-Origin: https://qaphr998two-ep.prismhr.com&#xd;
Access-Control-Allow-Methods: POST, PUT, PATCH, DELETE, GET, OPTIONS, HEAD&#xd;
Access-Control-Allow-Headers: Origin, X-Requested-With, Content-Type, Accept&#xd;
Access-Control-Allow-Credentials: true</responseHeaders>
    <record-html-infos extractorRegExp="false" htmlType="0"/>
    <textPostContent><![CDATA[{"prehireId":"${PreHire_ID}","step":"I9_SECTION1","workflow":{"prehireId":"${PreHire_ID}","wftId":"Sam_OB_WF.1.2","status":"","effectiveDate":"2019-05-10","hireDate":"2023-02-16","workflowDueDate":"2023-02-18","workflowCompletedDate":"","ssnRequired":"0","checksum":"${CS5}","prehireEmployeeId":"${Employee_ID}","clientId":"${clientId}","enableI9SupportingDocs":"Y","daysDueI9":"-15","daysDueWorkflow":"-13","enableBeAfterSubmit":"N","electronicConsent":"","createDate":"2023-02-16","prehireStatus":"","closeDate":"","forms":[{"formId":"INITIAL_VISIT.1.0","formName":"Initial Visit","status":"","usage":"OB_INITIAL_VISIT","offerType":"INITIAL_VISIT","completeDate":"","dueDate":"2023-02-18"},{"formId":"RETURN_VISIT.1.0","formName":"Return Visit","status":"","usage":"OB_RETURN_VISIT","offerType":"RETURN_VISIT","completeDate":"","dueDate":"2023-02-18"},{"formId":"I9_SECTION_ONE.1.0","formName":"I-9","status":"","usage":"OB_I9_SECTION_ONE","offerType":"I9_SECTION_ONE","completeDate":"","dueDate":"2023-02-16"},{"formId":"EMPLOYEE_INFORMATION.1.0","formName":"Employee Information","status":"","usage":"OB_EMPLOYEE_INFORMATION","offerType":"EMPLOYEE_INFORMATION","completeDate":"","dueDate":"2023-02-16"},{"formId":"DIRECT_DEPOSIT.1.0","formName":"Direct Deposit","status":"","usage":"OB_FORM_DIRECT_DEPOSIT","offerType":"DIRECT_DEPOSIT","completeDate":"","dueDate":"2023-02-18"},{"formId":"DISABILITY.1.0","formName":"Disability","status":"","usage":"OB_FORM_DISABILITY","offerType":"DISABILITY","completeDate":"","dueDate":"2023-02-18"},{"formId":"EEO.1.0","formName":"Race/Ethnicity","status":"","usage":"OB_FORM_EEO","offerType":"EEO","completeDate":"","dueDate":"2023-02-18"},{"formId":"VETERAN_STATUS.1.0","formName":"Veteran Status","status":"","usage":"OB_FORM_VETERAN","offerType":"VETERAN","completeDate":"","dueDate":"2023-02-18"},{"formId":"I9_SECTION_TWO.1.0","formName":"I-9 Section 2","status":"","usage":"OB_I9_SECTION_TWO","offerType":"I9_SECTION_TWO","completeDate":"","dueDate":"2023-02-19"},{"formId":"ONBOARDING_SUMMARY.1.0","formName":"Onboarding Summary","status":"","usage":"OB_SUMMARY","offerType":"ONBOARDING_SUMMARY","completeDate":"","dueDate":"2023-02-18"},{"formId":"ONBOARDING_SUBMIT.1.0","formName":"Submit","status":"","usage":"OB_SUBMIT","offerType":"ONBOARDING_SUBMIT","completeDate":"","dueDate":"2023-02-18"}],"tax":{"taxFileUUID":[]},"identity":{"i9LastName":"","i9FirstName":"","i9MiddleInitial":"","i9OtherLastName":"","i9Address":"","i9AptNumber":"","i9City":"","i9State":"","i9Zip":"","i9BirthDate":"","i9SSN":"","i9Email":"","i9Phone":"","i9CitizenStatus":"","i9AlienRegNo":"","i9AlienTypeNo":"","i9AlienExpDate":"","i9FormI94No":"","i9ForeignPassportNo":"","i9CountryIssuance":"","i9EmployeeSignature":"","i9PreparerUsed":"N","i9NumberOfPreparers":"","i9PrismVersion":"","i9DocumentToProvide":"","i9EmployeeSignDate":"","i9MgrDenyReason":"","i9ApprovalId":"","i9FileUUID":[],"i9UseSupportingDocs":"","i9SupportingDocs":{"code":[],"uuid":[]},"approvalPolicy":"","file":{},"fileSupplement":{}}},"account":"qaphr998two","peoId":"phr"}]]></textPostContent>
</http-action>
<http-action actionType="1"
    contentType="application/json; charset=utf-8"
    eTag="W/&quot;bef-KSdxY5K73698q+pBsEVviAYHIbM&quot;"
    extractorInjectPathPolicy="2" extractorPathPolicy="1"
    followRedirects="false" generatedByClient="false"
    linkExtractorSeveralMatchOccurrence="1"
    linkExtractorSeveralMatchPolicy="1" linkExtractorType="6"
    method="POST"
    name="/wave1/apis/obbe/rest2/qaphr998two/PREHIRE.RS.ONBOARD.DETAILS/GET_I9_SECTION1"
    path="/wave1/apis/obbe/rest2/qaphr998two/PREHIRE.RS.ONBOARD.DETAILS/GET_I9_SECTION1"
    postCharset="" postType="4"
    recordedArtifactZipFileName="team/vus/@o@b_@standard_@c4484603_@march/%resources%/recorded-artifacts/25e3c35d-6095-4195-b6f9-3c295ec0f489.zip"
    recordedResponseCode="200" responseSize="3055"
    serverUid="qaphr998two-ep.prismhr.com" slaProfileEnabled="false"
    uid="e1031d91-d97c-4b6c-b33d-126e06c01cee" useKeepAlive="false">
    <responsePageFileDescription>recorded-responses/res_24ab4321-f518-462d-9c90-df0a8ae376f0.0</responsePageFileDescription>
    <requestContentFileDescription>recorded-requests/req_24ab4321-f518-462d-9c90-df0a8ae376f0.txt</requestContentFileDescription>
    <variable-extractor assertionOnNoMatch="true"
        defaultValue="&lt;NOT FOUND>" displayMode="1" endsWithSimple=""
        extractFromVarNameAdv="" extractFromVarNameSimple=""
        extractType="0" extractTypeAdv="0" extractTypeSimple="0"
        matchNumber="1" matchNumberAdv="1" matchNumberSimple="1"
        name="CS5" regExp="&quot;checksum\\?&quot;:(.*?),"
        regExpAdv="&quot;checksum\\?&quot;:(.*?),"
        setDefaultValue="true" startsWithSimple="" template="$1$"
        templateAdv="$1$" uid="a2afdebd-c7d9-4378-8c59-92fe114acacb" xpath=""/>
    <variable-extractor assertionOnNoMatch="true"
        defaultValue="&lt;NOT FOUND>" displayMode="0" endsWithSimple=""
        extractFromVarNameAdv="" extractFromVarNameSimple=""
        extractType="4" extractTypeAdv="0" extractTypeSimple="4"
        jsonpath="$.response.workflow.prehireId" matchNumber="1"
        matchNumberAdv="1" matchNumberSimple="1" name="PreHire_ID"
        refererUid="ad287e79-701c-4a01-8711-1a06769a598a" regExp="(.*)"
        regExpAdv="" setDefaultValue="true" startsWithSimple=""
        template="$1$" templateAdv="$1$"
        uid="e93bc584-231e-4c63-adce-3740dcbff6fe" xpath="">
        <variable-extractor-group extract="true" occurs="1" pattern="" type="4"/>
    </variable-extractor>
    <header name="Accept" value="application/json"/>
    <header name="Accept-Encoding" value="gzip, deflate, br"/>
    <header name="Accept-Language" value="en-US,en;q=0.9"/>
    <header name="Access-Control-Allow-Methods" value="POST, GET, OPTIONS, PUT"/>
    <header name="Access-Control-Allow-Origin" value="*"/>
    <header name="Connection" value="keep-alive"/>
    <header name="Content-Type" value="application/json"/>
    <header name="Cookie" value="ESSauthToken=${ESSauthToken}; peoId=qaphr998two; accountId=qaphr998two; sails.sid=${sails_sid}; token=${Token}"/>
    <header name="Host" value="qaphr998two-ep.prismhr.com"/>
    <header name="Origin" value="https://qaphr998two-ep.prismhr.com"/>
    <header name="Referer" value="https://qaphr998two-ep.prismhr.com/obbe/"/>
    <header name="sec-ch-ua" value="&quot;Not_A Brand&quot;;v=&quot;99&quot;, &quot;Google Chrome&quot;;v=&quot;109&quot;, &quot;Chromium&quot;;v=&quot;109&quot;"/>
    <header name="sec-ch-ua-mobile" value="?0"/>
    <header name="sec-ch-ua-platform" value="&quot;Windows&quot;"/>
    <header name="Sec-Fetch-Dest" value="empty"/>
    <header name="Sec-Fetch-Mode" value="cors"/>
    <header name="Sec-Fetch-Site" value="same-origin"/>
    <header name="User-Agent" value="Mozilla/5.0 (Windows NT 10.0; Win64; x64) AppleWebKit/537.36 (KHTML, like Gecko) Chrome/109.0.0.0 Safari/537.36"/>
    <responseHeaders>HTTP/1.1 200 OK&#xd;
Date: Fri, 03 Mar 2023 09:55:17 GMT&#xd;
Content-Type: application/json; charset=utf-8&#xd;
Content-Length: 3055&#xd;
Connection: keep-alive&#xd;
X-Powered-By: Express&#xd;
Access-Control-Allow-Origin: *&#xd;
requestId: 2f812a8b6103bb034d5286910360ca07&#xd;
sessionId: rv8ppYHaH-zmnu7dgeoP-Zos5mrtEJuu&#xd;
ETag: W/"bef-K4KhhrQouM5n8wdh8AzczCuVryo"&#xd;
Strict-Transport-Security: max-age=31536000; includeSubDomains&#xd;
Access-Control-Allow-Origin: https://qaphr998two-ep.prismhr.com&#xd;
Access-Control-Allow-Methods: POST, PUT, PATCH, DELETE, GET, OPTIONS, HEAD&#xd;
Access-Control-Allow-Headers: Origin, X-Requested-With, Content-Type, Accept&#xd;
Access-Control-Allow-Credentials: true</responseHeaders>
    <record-html-infos extractorRegExp="false" htmlType="0"/>
    <textPostContent><![CDATA[{"prehireId":"${PreHire_ID}","account":"qaphr998two","peoId":"phr"}]]></textPostContent>
</http-action>
<http-action actionType="1"
    contentType="application/json; charset=utf-8"
    eTag="W/&quot;c76b-oiew5YFLjiLq4mq5356KC0rqZm0&quot;"
    extractorInjectPathPolicy="2" extractorPathPolicy="1"
    followRedirects="false" generatedByClient="false"
    linkExtractorSeveralMatchOccurrence="1"
    linkExtractorSeveralMatchPolicy="1" linkExtractorType="6"
    method="POST"
    name="/wave1/apis/obbe/rest2/qaphr998two/PREHIRE.RS.I9.ENGINE/GET_DETAILS"
    path="/wave1/apis/obbe/rest2/qaphr998two/PREHIRE.RS.I9.ENGINE/GET_DETAILS"
    postType="4"
    recordedArtifactZipFileName="team/vus/@o@b_@standard_@c4484603_@march/%resources%/recorded-artifacts/25e3c35d-6095-4195-b6f9-3c295ec0f489.zip"
    recordedResponseCode="200" responseSize="51051"
    serverUid="qaphr998two-ep.prismhr.com" slaProfileEnabled="false"
    uid="c131e25e-ae95-4af6-a2d0-231cbc84c2fc" useKeepAlive="false">
    <responsePageFileDescription>recorded-responses/res_c5179386-ba33-412d-ad01-d69d19c010e5</responsePageFileDescription>
    <requestContentFileDescription>recorded-requests/req_c5179386-ba33-412d-ad01-d69d19c010e5.txt</requestContentFileDescription>
    <header name="Accept" value="application/json"/>
    <header name="Accept-Encoding" value="gzip, deflate, br"/>
    <header name="Accept-Language" value="en-US,en;q=0.9"/>
    <header name="Access-Control-Allow-Methods" value="POST, GET, OPTIONS, PUT"/>
    <header name="Access-Control-Allow-Origin" value="*"/>
    <header name="Connection" value="keep-alive"/>
    <header name="Content-Type" value="application/json"/>
    <header name="Cookie" value="ESSauthToken=${ESSauthToken}; peoId=qaphr998two; accountId=qaphr998two; sails.sid=${sails_sid}; token=${Token}"/>
    <header name="Host" value="qaphr998two-ep.prismhr.com"/>
    <header name="Origin" value="https://qaphr998two-ep.prismhr.com"/>
    <header name="Referer" value="https://qaphr998two-ep.prismhr.com/obbe/"/>
    <header name="sec-ch-ua" value="&quot;Not_A Brand&quot;;v=&quot;99&quot;, &quot;Google Chrome&quot;;v=&quot;109&quot;, &quot;Chromium&quot;;v=&quot;109&quot;"/>
    <header name="sec-ch-ua-mobile" value="?0"/>
    <header name="sec-ch-ua-platform" value="&quot;Windows&quot;"/>
    <header name="Sec-Fetch-Dest" value="empty"/>
    <header name="Sec-Fetch-Mode" value="cors"/>
    <header name="Sec-Fetch-Site" value="same-origin"/>
    <header name="User-Agent" value="Mozilla/5.0 (Windows NT 10.0; Win64; x64) AppleWebKit/537.36 (KHTML, like Gecko) Chrome/109.0.0.0 Safari/537.36"/>
    <responseHeaders>HTTP/1.1 200 OK&#xd;
Date: Fri, 03 Mar 2023 09:55:17 GMT&#xd;
Content-Type: application/json; charset=utf-8&#xd;
Content-Length: 51051&#xd;
Connection: keep-alive&#xd;
X-Powered-By: Express&#xd;
Access-Control-Allow-Origin: *&#xd;
requestId: 8555ece68f1a0a9d520c35f82e299664&#xd;
sessionId: rv8ppYHaH-zmnu7dgeoP-Zos5mrtEJuu&#xd;
ETag: W/"c76b-oiew5YFLjiLq4mq5356KC0rqZm0"&#xd;
Strict-Transport-Security: max-age=31536000; includeSubDomains&#xd;
Access-Control-Allow-Origin: https://qaphr998two-ep.prismhr.com&#xd;
Access-Control-Allow-Methods: POST, PUT, PATCH, DELETE, GET, OPTIONS, HEAD&#xd;
Access-Control-Allow-Headers: Origin, X-Requested-With, Content-Type, Accept&#xd;
Access-Control-Allow-Credentials: true</responseHeaders>
    <record-html-infos extractorRegExp="false" htmlType="0"/>
    <textPostContent><![CDATA[{"prehireId":"${PreHire_ID}","account":"qaphr998two","peoId":"phr"}]]></textPostContent>
</http-action>
